{
 "mdsDat": {
 "x": [ 0.2187125, -0.1294139, -0.06040672, -0.1992138, -0.1164111, 0.170151, -0.0305303, -0.08459464, 0.2317069 ],
"y": [ -0.1546984, 0.1614681, 0.08114813, -0.08881223, -0.02526686, 0.03212833, 0.126338, -0.2151272, 0.08282225 ],
"topics": [ 1, 2, 3, 4, 5, 6, 7, 8, 9 ],
"Freq": [ 14.26533, 12.51649,  12.4449, 12.09331, 11.79884, 10.82931, 10.35008, 8.622974, 7.078772 ],
"cluster": [        1,        1,        1,        1,        1,        1,        1,        1,        1 ] 
},
"tinfo": {
 "Term": [ "product", "employe", "board", "store", "risk", "wast", "financi", "asset", "emiss", "energi", "member", "manag", "report", "share", "custom", "sustain", "tax", "statement", "food", "supplier", "incom", "chain", "committe", "train", "sale", "audit", "liabil", "compani", "suppli", "gri", "liabil", "asset", "expens", "impair", "hedg", "cash", "ifr", "non-curr", "depreci", "currenc", "intang", "debt", "goodwil", "loan", "amortis", "amort", "payabl", "defer", "right-of-us", "accru", "interest-bear", "non-control", "ia", "recover", "deduct", "incur", "actuari", "sheet", "dilut", "equiti", "colleagu", "children", "fairer", "chariti", "proud", "tackl", "healthier", "youth", "volunt", "cancer", "co-oper", "champion", "voucher", "fareshar", "fundrais", "disadvantag", "feel", "explor", "breast", "charit", "bed", "think", "voic", "hunger", "sure", "say", "asda", "creativ", "neighborhood", "nhs", "103-2", "amfori", "bsci", "103-1", "bangladesh", "ie", "tab", "ppli", "103-3", "iro", "ontent", "mploy", "mmu", "nit", "grievanc", "gri", "high-risk", "polit", "human", "sustainabilit", "nme", "thailand", "non-government", "ilo", "irish", "factori", "dialog", "bepi", "migrant", "multi-stakehold", "fish", "meat", "palm", "cocoa", "soy", "egg", "veget", "cotton", "own-brand", "salt", "seafood", "reusabl", "bottl", "tea", "milk", "speci", "certifi", "pesticid", "fsc", "sugar", "fat", "flower", "juic", "rspo", "husbandri", "beef", "fisheri", "southwest", "poultri", "tuna", "norgesgruppen", "norway", "omnichannel", "cater", "kiwi", "hemköp", "meni", "norwegian", "spar", "e-commerc", "popular", "okay", "trumf", "mnok", "deli", "dreamland", "pick-up", "bio-planet", "bnok", "joker", "s-bank", "wholesal", "retailer-own", "cus-", "tomer", "webshop", "storekeep", "foodservic", "cru", "soluci", "opinion", "fraud", "misstat", "error", "whistleblow", "procedur", "verif", "manage-", "confidenti", "breach", "kpmg", "defici", "isa", "clarifi", "launder", "carrefour", "deloitt", "publ", "agement", "spt", "hereinaft", "inher", "cms", "appetit", "grc", "dnv", "privaci", "failur", "english", "discrep", "men", "accid", "workforc", "femal", "traine", "boss", "injuri", "ill", "madrid", "sexual", "e-learn", "work-lif", "seminar", "valencia", "mercadona", "hire", "graduat", "apprenticeship", "apprentic", "internship", "supercor", "disabl", "xx.x", "ergonom", "roig", "career", "postpon", "smes", "rehabilit", "doctor", "wast", "emiss", "carbon", "refriger", "gas", "greenhous", "ghg", "heat", "energi", "truck", "electr", "co2", "solar", "kwh", "photovolta", "halv", "roof", "mwh", "landfil", "gwh", "fossil", "diesel", "cdp", "gase", "dioxid", "bioga", "k-food", "co2e", "low-carbon", "rainwat", "vote", "sok", "agm", "tsr", "gro", "jan", "vest", "chair", "roc", "edingensesteenweg", "deputi", "fran", "kevin", "natali", "kori", "statut", "ltip", "reappoint", "axel", "förbund", "ben", "wouter", "jef", "directorship", "cfo", "tel", "remuner", "knight", "holt", "osuuskauppa", "leas", "instrument", "tax", "donat", "get", "big", "littl", "labor", "dilig", "fruit", "farmer", "asko", "conveni", "law", "document", "legisl", "gender", "leav", "del", "wind", "cool", "execut", "chairman", "supervisori", "incom", "note", "ventur", "communiti", "stakehold", "coffe", "dairi", "growth", "assur", "adequ", "train", "occup", "fuel", "fleet", "elect", "accumul", "sto", "audit", "evid", "recoveri", "renew", "board", "short-term", "loss", "help", "messag", "child", "ireland", "fairtrad", "label", "neighbourhood", "regul", "sampl", "employe", "job", "consumpt", "hydrogen", "committe", "head", "vice", "net", "everyon", "labour", "packag", "groceri", "shop", "onlin", "willi", "risk", "women", "transport", "peter", "flow", "lifestyl", "topic", "plastic", "autom", "control", "overse", "baselin", "director", "chief", "amount", "eat", "right", "farm", "oil", "coronavirus", "territori", "air", "sharehold", "cost", "poverti", "supplier", "bag", "matter", "descript", "regulatori", "talent", "vehicl", "profit", "reserv", "healthi", "paper", "format", "suffici", "age", "ceo", "peopl", "suppli", "restaur", "reduct", "member", "wellb", "chain", "product", "store", "appropri", "log", "tonn", "senior", "presid", "pension", "support", "approach", "environment", "strong", "data", "prepar", "cours", "scope", "social", "recycl", "anim", "sale", "deliveri", "deviat", "personnel", "enseign", "zero", "trend", "inform", "auditor", "reduc", "instal", "compens", "nomin", "financi", "want", "global", "obtain", "safeti", "recruit", "interest", "know", "compact", "organ", "market", "demand", "report", "complianc", "meet", "rate", "better", "transpar", "concept", "concern", "portug", "across", "sustain", "respons", "custom", "propos", "school", "protect", "code", "divers", "climat", "share", "foundat", "intern", "make", "wage", "agricultur", "supermarket", "accord", "account", "statement", "skill", "light", "grant", "transact", "equal", "properti", "need", "produc", "health", "provis", "countri", "fresh", "local", "price", "footprint", "appoint", "consolid", "privat", "assess", "hour", "euro", "access", "resourc", "requir", "polici", "general", "capit", "employ", "worker", "increas", "work", "effici", "famili", "retail", "regard", "warehous", "salari", "young", "impact", "servic", "valu", "food", "standard", "offer", "applic", "campaign", "financi", "target", "statement", "partnership", "manag", "govern", "invest", "home", "sdg", "environ", "govern", "workplac", "creat", "good", "store", "develop", "strategi", "manag", "manag", "principl", "area", "compani", "water", "brand", "system", "fund", "welfar", "perform", "annual", "compani", "corpor", "total", "custom", "commit", "rang", "develop", "receiv", "work", "action", "work", "consum", "food", "respons", "promot", "product", "certif", "result", "group", "perform", "logist", "benefit", "oper", "provid", "food", "live", "repres", "oper", "covid-19", "climat", "use", "food", "sustain", "product", "basi", "way", "share", "continu", "includ", "materi", "pandem", "review", "annual", "project", "relat", "goal", "brand", "social", "total", "oper", "report", "activ", "compani", "offic", "member", "sinc", "number", "manag", "compani", "servic", "initi", "use", "activ", "commit", "total", "implement", "chang", "health", "continu", "retail", "support", "report", "region", "end", "opportun", "includ", "report", "corpor", "offer", "plan", "valu", "custom", "oper", "measur", "sustain", "valu", "consolid", "report", "brand", "sustain", "develop", "sustain", "measur", "product", "sourc", "provid", "store", "impact", "materi", "commit", "annual", "includ", "relat", "number", "associ", "associ", "project", "process", "sinc", "time", "reduc", "plan" ],
"logprob": [       30,       29,       28,       27,       26,       25,       24,       23,       22,       21,       20,       19,       18,       17,       16,       15,       14,       13,       12,       11,       10,        9,        8,        7,        6,        5,        4,        3,        2,        1,  -4.3853,  -3.9774,  -5.0265,  -5.3146,  -5.6141,  -4.4331,  -5.7097,  -5.8341,  -5.8925,  -6.0438,  -6.0635,  -6.0875,  -6.1164,  -6.2268,  -6.4687,  -6.6873,  -6.7097,  -5.9162,  -6.8217,  -7.1035,  -7.1262,  -7.1613,  -7.2482,  -7.2612,  -7.2745,  -7.2879,  -7.3292,  -5.7939,  -7.4174,  -5.2741,  -4.9808,  -5.2155,  -5.5438,  -5.8668,  -6.6128,  -6.6286,  -6.1133,   -6.932,  -6.9537,  -7.0336,  -7.0824,  -7.2301,  -7.3209,  -7.3209,  -7.3369,  -7.4385,  -6.6608,  -7.4748,  -7.5319,  -7.6134,  -7.6568,  -6.8695,  -7.6792,  -7.6792,  -6.8796,  -6.5021,  -7.8254,  -7.8793,  -8.0284,  -8.0949,  -6.3382,  -6.3503,  -6.4933,  -6.5657,   -6.934,  -7.0248,  -7.0368,  -7.0368,  -7.0368,  -7.0489,  -7.0611,  -7.0611,  -7.0611,  -7.0611,  -7.5037,  -4.3379,  -6.7738,  -6.7831,  -4.5059,  -6.9784,  -7.0736,  -7.9275,  -8.0196,  -8.0196,  -8.0196,  -6.5074,  -7.3443,  -8.2746,   -8.317,  -8.3613,   -5.041,  -5.3875,  -5.4797,  -5.7272,  -5.7965,  -5.8942,  -5.1418,  -5.9766,  -5.3594,  -6.3398,  -6.3585,  -6.4101,  -6.4715,  -6.4928,  -6.5674,  -6.6909,  -4.8999,  -6.7176,  -6.7266,  -5.9387,  -6.7636,  -6.7923,  -6.8219,   -6.842,   -6.961,  -6.9842,  -7.0323,  -7.0447,  -7.0573,    -7.15,  -6.2103,   -6.599,  -6.7301,  -6.7585,  -6.7977,  -6.8077,   -6.881,  -6.9838,   -7.085,  -5.9481,  -7.2434,  -7.4701,   -7.573,  -6.7779,   -7.595,  -7.6638,  -7.6878,  -7.7377,  -7.7377,  -7.8745,  -7.9043,  -5.6541,   -7.935,  -7.9666,  -7.9666,  -7.9993,  -7.9993,  -6.4403,  -8.0331,  -8.0331,  -5.8482,  -6.8005,   -6.857,  -6.8687,  -7.2503,  -5.4178,   -7.549,  -7.6211,  -7.6464,  -7.7262,   -7.813,  -7.9418,  -7.9418,  -8.0506,  -8.0896,  -8.0896,  -8.2169,  -8.2169,  -8.2169,  -8.2169,  -8.2632,  -8.3628,  -8.4734,  -8.4734,  -8.5978,  -8.5978,  -7.0626,   -7.813,  -7.8436,  -8.6663,  -5.9853,  -6.0371,  -6.0973,  -6.1318,  -6.6191,  -6.7404,   -6.842,  -6.9686,  -6.9822,  -7.2649,  -7.2832,  -7.3403,  -7.3403,  -7.4218,  -7.4652,  -6.7731,  -7.5827,  -6.8185,   -6.854,  -7.7158,  -7.7158,  -5.9312,  -7.7447,  -7.9033,  -7.9383,  -6.1736,  -7.9745,  -7.9745,  -8.0918,  -8.0918,  -3.5653,  -3.7308,  -4.9264,  -5.0214,  -5.0665,  -5.3671,  -5.3971,  -5.4039,  -3.7886,  -5.7692,  -4.6774,   -5.387,  -6.3773,   -6.598,  -6.8966,  -7.0256,  -7.0969,  -7.1156,  -7.1939,  -7.2145,   -7.257,  -7.2789,  -7.2789,  -7.3013,  -7.3243,  -7.3718,  -7.4217,  -7.4476,  -7.5296,  -7.5296,  -5.8092,  -5.4864,  -6.4295,  -6.5932,  -6.6939,  -6.7563,  -5.9864,  -5.5664,  -6.8579,  -6.9128,  -7.0542,  -7.0761,   -7.145,   -7.169,  -6.5399,  -7.4162,  -7.4805,  -7.5143,  -7.5493,  -7.5493,  -7.5855,  -7.6231,  -7.6231,  -7.6231,  -6.8759,  -7.7028,  -4.4681,  -7.7894,  -7.7894,  -7.7894,  -4.7494,  -5.6041,  -4.1908,  -4.8562,  -6.1618,   -6.669,  -6.5233,  -5.8655,  -6.5885,  -5.0893,  -5.6256,  -7.2434,     -6.1,  -5.2696,  -6.0087,  -6.4519,  -5.5243,  -6.1858,  -6.9552,  -6.3684,  -6.9431,   -4.199,  -5.3278,  -4.6485,   -4.235,  -4.5919,  -6.4747,  -4.3532,  -4.8733,  -5.8479,  -6.3904,  -4.7599,  -5.3208,  -7.5036,  -4.1295,  -5.4626,   -5.377,  -6.4329,  -6.1306,  -6.5301,  -7.0988,  -4.1308,  -6.5842,  -6.3955,  -5.1633,  -3.2901,  -6.5051,  -4.8339,  -4.4939,  -6.9759,  -6.0537,  -6.3625,  -5.4902,  -4.5548,  -7.6403,    -5.46,  -7.1678,  -3.2827,  -5.5275,  -4.2942,  -6.7824,  -3.9466,  -5.0211,  -6.1928,   -4.448,  -6.1973,  -5.8361,  -4.3075,  -5.3146,  -4.7067,  -4.6932,  -6.9959,  -3.5951,  -5.1893,  -4.8072,   -6.971,  -5.1813,  -6.8107,  -5.2047,  -4.5242,    -6.96,  -4.6055,  -7.6211,  -6.4424,  -4.0748,  -5.6534,   -4.448,  -6.0185,  -4.3526,  -5.1759,  -5.3995,  -6.3662,  -6.9822,  -6.5018,  -4.5605,  -4.8098,  -6.9002,  -4.0172,  -5.6256,  -5.6667,  -6.3918,  -6.7896,  -6.1318,  -5.9752,  -4.8961,  -5.9689,   -5.099,  -5.7682,  -6.1616,  -6.6671,  -5.7207,  -4.7069,  -4.3906,  -4.1349,  -6.1406,  -4.8434,  -3.7327,  -6.2181,  -4.0213,  -2.9868,  -3.5726,  -5.8149,  -6.9033,  -5.1188,  -5.4729,  -5.9285,  -5.2563,  -4.0558,  -4.8788,  -4.6172,  -5.6259,    -4.51,  -5.4543,  -5.6107,  -4.5597,  -4.3584,  -4.7005,  -4.8078,  -3.9874,  -5.5542,  -6.9168,   -5.936,    -5.88,   -5.712,  -6.2103,  -4.2091,  -5.6527,  -4.1621,   -6.012,   -5.257,  -5.9498,  -3.7541,  -5.5226,  -5.0399,   -6.097,  -4.6632,  -6.3105,  -4.9036,  -6.4677,  -6.5508,  -4.7198,  -4.5347,  -5.6898,  -3.4496,  -5.2937,  -4.2437,  -4.7441,  -5.2174,  -5.4752,  -5.9228,  -5.5853,  -5.9954,  -5.3993,  -3.5558,  -4.2306,  -3.9678,  -5.4685,  -5.7649,  -4.8555,  -5.4041,  -5.2749,  -4.3638,  -3.7532,  -5.5173,  -4.6403,   -4.689,  -6.0857,  -5.6408,  -5.7165,  -4.8956,  -4.6712,  -4.4208,  -5.9312,   -5.779,  -5.2114,  -5.6502,  -5.5023,  -5.3528,  -5.1537,  -4.9117,  -4.6353,  -5.5131,   -4.969,  -5.3433,  -4.9173,  -5.2298,  -5.7594,  -5.8155,  -4.8362,  -5.3571,  -5.1724,  -5.7888,  -5.8754,   -5.732,  -5.3341,   -4.873,  -4.8619,  -4.8398,  -5.4403,  -5.1042,  -5.7594,  -4.6341,  -4.0713,  -5.1606,  -5.8485,  -4.5826,  -5.6218,  -5.4349,  -5.5001,   -5.924,  -4.7784,   -4.747,  -4.3677,  -4.2459,  -4.9797,  -4.9919,  -5.7438,  -5.7385,   -4.219,   -4.606,  -4.5811,  -5.5961,  -4.2099,   -4.473,  -4.8657,  -5.6446,  -5.3477,  -5.3167,  -4.8446,  -6.1376,  -5.3606,  -5.0528,  -4.0684,  -4.6768,  -5.0868,  -4.3318,  -3.9862,  -5.4651,  -5.0286,  -4.3483,  -5.2014,  -5.0168,  -4.8911,  -5.6364,  -5.4141,  -4.8051,  -4.4747,  -4.0649,  -4.6863,  -4.6424,  -4.6175,  -4.9273,  -5.1474,  -4.6525,  -5.1411,  -4.5658,  -5.3698,  -4.5856,  -5.3997,  -4.6215,   -4.695,  -5.1985,  -4.3092,  -5.5333,  -5.0829,  -4.9459,   -4.631,   -5.241,  -5.1979,  -4.8189,  -5.1042,  -4.3723,  -5.6364,  -5.3087,  -4.6187,  -5.4323,  -5.1781,   -4.774,  -4.5652,  -4.4258,  -4.5254,  -5.4014,   -5.489,  -4.7764,  -5.1322,  -4.7903,  -5.0893,  -5.4477,  -5.3308,  -4.9684,  -5.3051,  -5.0585,  -5.3859,  -5.1143,  -5.2749,  -5.1825,  -4.7126,  -4.7746,   -5.253,  -4.6975,  -5.2789,  -5.2609,  -5.2396,  -5.3603,  -4.9042,  -4.8247,  -5.3257,  -5.3764,  -5.1307,     -5.3,     -5.3,  -4.9096,  -5.5633,  -4.9946,  -5.3924,  -5.3562,  -5.3154,  -5.3076,   -4.721,  -5.4068,  -5.3075,   -5.679,  -4.9161,  -4.9605,   -5.221,  -5.5469,  -5.0535,  -5.3517,  -5.1486,  -5.0977,  -5.4992,   -4.883,  -5.1932,  -5.2649,  -4.9739,  -5.4615,  -5.1481,  -5.5147,  -5.4452,  -5.2182,  -5.0961,  -5.4288,  -5.2744,  -5.5339,  -5.2296,  -5.2912,  -5.5935,  -5.5746,  -5.1986,  -5.1395,  -5.5894,  -5.4336,  -5.4967,  -5.4514,  -5.2961,  -5.4422,  -5.6044,  -5.4514,  -5.5969 ],
"loglift": [       30,       29,       28,       27,       26,       25,       24,       23,       22,       21,       20,       19,       18,       17,       16,       15,       14,       13,       12,       11,       10,        9,        8,        7,        6,        5,        4,        3,        2,        1,   1.9467,   1.9465,   1.9462,   1.9458,   1.9453,   1.9452,   1.9451,   1.9448,   1.9447,   1.9442,   1.9442,   1.9441,    1.944,   1.9436,   1.9426,   1.9414,   1.9413,   1.9412,   1.9406,   1.9384,   1.9382,   1.9379,    1.937,   1.9369,   1.9367,   1.9366,   1.9361,   1.9359,   1.9351,   1.9334,   2.0769,   2.0766,    2.076,   2.0752,   2.0719,   2.0718,   2.0696,   2.0695,   2.0693,   2.0686,   2.0681,   2.0666,   2.0655,   2.0655,   2.0653,   2.0639,   2.0634,   2.0634,   2.0625,   2.0612,   2.0605,   2.0601,   2.0601,   2.0601,   2.0599,   2.0587,   2.0572,   2.0561,   2.0526,   2.0509,   2.0791,    2.079,   2.0783,   2.0779,   2.0752,   2.0744,   2.0743,   2.0743,   2.0743,   2.0742,    2.074,    2.074,    2.074,    2.074,   2.0686,   2.0679,   2.0673,   2.0672,   2.0659,   2.0636,   2.0616,   2.0606,   2.0584,   2.0584,   2.0584,   2.0572,   2.0549,   2.0512,   2.0498,   2.0483,   2.1112,   2.1106,   2.1104,   2.1098,   2.1097,   2.1094,   2.1092,   2.1091,   2.1084,   2.1076,   2.1075,   2.1072,   2.1069,   2.1068,   2.1063,   2.1055,   2.1055,   2.1053,   2.1053,   2.1051,    2.105,   2.1048,   2.1045,   2.1044,   2.1034,   2.1032,   2.1027,   2.1026,   2.1024,   2.1015,   2.1327,   2.1306,   2.1297,   2.1295,   2.1292,   2.1291,   2.1285,   2.1276,   2.1266,   2.1252,   2.1247,   2.1216,   2.1199,   2.1197,   2.1196,   2.1183,   2.1179,   2.1169,   2.1169,   2.1139,   2.1132,   2.1126,   2.1125,   2.1117,   2.1117,   2.1109,   2.1109,   2.1108,     2.11,     2.11,   2.2195,   2.2142,   2.2137,   2.2136,   2.2093,   2.2071,   2.2046,   2.2033,   2.2028,   2.2011,   2.1991,   2.1959,   2.1959,   2.1929,   2.1917,   2.1917,   2.1875,   2.1875,   2.1875,   2.1875,   2.1859,   2.1821,   2.1774,   2.1774,   2.1715,   2.1715,   2.1705,   2.1703,   2.1687,    2.168,   2.2641,   2.2639,   2.2637,   2.2635,   2.2606,   2.2596,   2.2587,   2.2574,   2.2573,   2.2537,   2.2535,   2.2526,   2.2526,   2.2513,   2.2505,   2.2484,   2.2484,   2.2475,   2.2467,   2.2456,   2.2456,   2.2454,   2.2449,    2.241,     2.24,   2.2391,    2.239,    2.239,   2.2354,   2.2354,   2.4503,   2.4502,   2.4491,   2.4489,   2.4488,   2.4481,    2.448,    2.448,   2.4468,   2.4468,   2.4462,   2.4448,   2.4436,   2.4418,   2.4387,   2.4371,   2.4361,   2.4358,   2.4346,   2.4343,   2.4336,   2.4332,   2.4332,   2.4328,   2.4324,   2.4315,   2.4305,     2.43,   2.4282,   2.4282,   2.6431,     2.64,   2.6389,   2.6373,   2.6361,   2.6354,   2.6348,   2.6346,    2.634,   2.6332,    2.631,   2.6306,   2.6294,   2.6289,   2.6251,   2.6236,    2.622,   2.6211,   2.6202,   2.6202,   2.6192,   2.6181,   2.6181,   2.6181,   2.6162,   2.6156,   2.6149,   2.6128,   2.6128,   2.6128,   1.9327,   1.9254,   1.9078,   2.0451,   2.0496,   2.0471,   2.0443,   2.0408,   2.0327,   2.0937,   2.0922,   2.1094,   2.0943,   2.1589,   2.1615,   2.1645,   2.2221,   2.2271,   2.2313,   2.4173,   2.4225,   2.6021,   2.6002,   2.5842,   1.9044,   1.9045,   1.9249,   1.9989,   2.0046,   2.0872,   2.0944,   2.0656,   2.1376,   2.1629,   2.1734,   2.1909,   2.3967,   2.4153,   2.5915,   1.9235,   2.0363,   2.0766,   2.1403,   2.4078,   2.3693,   2.4966,   1.9182,   1.8458,   1.9544,   2.0361,   1.9946,   2.0029,   2.0568,   2.0161,   2.0963,   2.0849,   2.1501,   2.0892,   2.1629,   2.3201,   2.4138,   2.4885,   2.5218,   2.5627,   1.8265,   1.9997,   1.9621,   1.9737,   1.9882,   1.9535,   1.9506,   2.0684,   1.9463,   2.1126,   2.3085,    2.594,   1.8373,   2.0242,   1.9164,   1.9765,   2.0602,   1.9894,   2.1556,   2.3874,   2.4316,   2.5196,   1.7833,   1.9608,   1.8599,   1.9897,   2.0055,   2.0052,   2.1916,   2.3838,   2.4091,   1.7887,   2.0193,   1.7972,   2.0156,   1.9952,   2.0571,    2.084,   2.1229,    2.333,   1.7704,    1.875,   1.8485,   2.0168,   1.9683,   2.0577,   2.0777,   2.3684,   1.7563,   1.7656,   1.9582,    2.187,   2.2652,   1.9414,   1.7029,   1.6611,   1.6287,   1.9444,   2.1854,   2.2138,   2.4382,   2.4884,   1.7867,   1.6601,   1.8013,   1.7569,   1.8589,   1.7674,   1.8704,   2.0182,   2.1169,   1.6792,   1.8439,   1.8587,   1.6096,   1.8274,   2.0656,    2.053,   2.0383,   2.2547,    1.923,   1.6413,   1.8648,   1.9984,   2.2963,   2.3567,   2.4553,   1.5001,    1.794,   1.7458,   1.9346,   1.7951,    2.085,   1.6998,   1.9463,   1.9866,   1.7757,   1.6253,   1.8183,   1.4253,   1.7653,   2.1392,   1.6681,   1.7041,   1.7721,   1.8561,   1.8145,   2.0053,   1.7122,   1.3386,    1.465,   1.4086,   2.3358,   1.7795,   1.5712,   1.7405,   1.8441,   1.9123,    1.911,   1.7118,   1.5568,   1.4858,   1.8498,   1.8961,   1.7659,   1.5995,   1.5389,   1.4697,   1.9877,   2.2118,   2.2359,   1.8216,   1.8676,   1.7323,   1.5471,    1.677,   1.5905,   1.7776,   1.5096,   1.7922,   1.4193,   1.5727,   2.1671,   2.3575,    1.545,   1.7767,   1.6133,   1.9042,   1.9243,   1.6775,   1.5394,   1.4965,   1.4841,   1.9962,     1.75,   1.6109,    1.673,   1.2121,   1.1694,   1.9111,   1.7055,   1.1904,   1.7316,   2.0135,   2.1813,   1.7361,   1.2497,   1.2324,   1.2519,   0.9518,   1.3133,   1.2921,   1.7633,   1.6433,   1.0352,   1.5631,   1.3094,   1.5699,   0.9847,   1.6331,   1.4371,   1.5397,   1.9078,   1.3899,   1.2615,   1.9848,   1.3856,   1.1252,   1.1328,   0.9646,   1.2112,   0.8628,   1.2084,    1.438,   1.0854,   0.8289,   1.8088,   1.0739,   1.5836,   1.5346,     1.71,   1.1523,   1.4247,   1.1124,   1.5525,   1.1233,   0.7588,   1.0382,   1.5091,   0.9889,   1.4799,   0.6749,   1.3089,   0.6551,   1.2433,   0.5762,   1.0006,   1.3456,   0.3387,   1.7769,   0.9532,   1.2032,   1.3264,   1.6977,   1.5079,    0.646,   0.9609,   0.8255,   1.4878,   1.9043,   0.8462,    1.259,    1.098,   1.2145,   0.6326,   0.4686,   0.1225,     1.56,    1.303,   0.8878,   0.8014,   0.7168,   1.0931,   1.1889,   1.4623,    0.931,   0.9783,   1.0444,   1.2055,   0.9764,   0.7627,   0.5831,   0.7523,   0.1002,   0.6256,   0.4798,   1.6507,    0.737,   1.1479,   0.8196,   0.2904,   0.3526,   0.6536,   0.8777,   0.8578,   0.5786,   0.6655,    0.856,   1.1175,   0.9597,   0.8335,   0.5774,   0.4576,   0.4083,   0.1538,   1.3975,   1.0463,   1.3669,    0.591,  -0.0857,   1.0178,   0.7371,   0.9455,   0.2679,   0.2278,   0.3672,   0.5163,   0.0113,   0.4264,   1.1164,   -0.099,   0.6292,  -0.2538,   0.1267,  -0.5508,   0.7973,  -0.4481,   1.2969,   0.7907,  -0.3327,   0.7985,   0.8911,    0.372,   0.3248,   0.3084,   0.9634,   0.5904,   0.8071,    0.744,    0.832,   1.0479,   0.9453,   0.7376,   0.7091,   0.4021 ],
"Freq": [     7052,     3418,     2258,     4055,     2885,     1796,     3846,     1968,     1522,     1441,     1828,     4082,     5620,     2552,     3404,     5512,     1653,     2035,     4069,     2196,     1586,     2403,     1180,     1347,     2729,     1482,     1308,     4153,     2015,     1215, 1308.119, 1966.974, 688.9884, 516.5233, 382.8144, 1247.078, 347.9338, 307.2398, 289.7995, 249.1055,  244.261, 238.4475, 231.6652, 207.4426, 162.8729, 130.8991, 127.9924, 283.0172, 114.4277, 86.32944, 84.39163, 81.48491, 74.70258, 73.73367, 72.76477, 71.79586, 68.88915, 319.8355, 63.07572, 537.8392,  632.739, 500.4153, 360.3647, 260.8805, 123.7275, 121.7957, 203.8944, 89.92215, 87.99041, 81.22935, 77.36589, 66.74136, 60.94616, 60.94616, 59.98029,  54.1851, 117.9323, 52.25336, 49.35576,  45.4923, 43.56057, 95.71734,  42.5947,  42.5947, 94.75148, 138.2155,  36.7995, 34.86777, 30.03844, 28.10671,  161.892, 159.9543,   138.64, 128.9517, 89.22952, 81.47885, 80.51002, 80.51002, 80.51002, 79.54119, 78.57236, 78.57236, 78.57236, 78.57236,  50.4762, 1196.606, 104.7308,  103.762, 1011.559, 85.35419, 77.60352,  33.0372, 30.13071, 30.13071, 30.13071, 136.7023,  59.1957, 23.34888, 22.38004, 21.41121, 575.6711, 407.0686, 371.2163,  289.822, 270.4424, 245.2489, 520.4392, 225.8693, 418.6963, 157.0717, 154.1647, 146.4129, 137.6921, 134.7851, 125.0953, 110.5606, 662.8793, 107.6537, 106.6847, 234.5901, 102.8088, 99.90185, 96.99491, 95.05695, 84.39817, 82.46021, 78.58429, 77.61531, 76.64633, 69.86347,  174.432, 118.2573, 103.7294, 100.8238, 96.94971, 95.98118, 89.20148, 80.48472, 72.73649, 226.7325, 62.08268, 49.49181, 44.64917, 98.88676, 43.68064, 40.77505, 39.80652, 37.86947, 37.86947, 33.02682, 32.05829, 304.2148, 31.08977, 30.12124, 30.12124, 29.15271, 29.15271, 138.5964, 28.18418, 28.18418, 229.9525, 88.72795, 83.85814, 82.88418,  56.5872, 353.6457, 41.97777, 39.05588, 38.08192, 35.16003, 32.23815,  28.3423,  28.3423, 25.42041, 24.44645, 24.44645, 21.52456, 21.52456, 21.52456, 21.52456,  20.5506, 18.60268, 16.65475, 16.65475, 14.70683, 14.70683, 68.27475, 32.23815, 31.26419, 13.73287, 191.6344, 181.9608, 171.3198, 165.5157, 101.6698, 90.06142, 81.35516, 71.68154, 70.71417, 53.30166, 52.33429, 49.43221, 49.43221, 45.56276, 43.62803, 87.15933, 38.79122, 83.28988,  80.3878, 33.95441, 33.95441, 202.2754, 32.98705, 28.15024, 27.18288, 158.7441, 26.21551, 26.21551, 23.31343, 23.31343, 1795.374, 1521.568, 460.3249, 418.5743, 400.1264, 296.2353, 287.4968, 285.5549, 1436.124, 198.1698, 590.4315, 290.4096,  107.872, 86.51118, 64.17945, 56.41189, 52.52811, 51.55717, 47.67339, 46.70244, 44.76056, 43.78961, 43.78961, 42.81867, 41.84772, 39.90583, 37.96394,   36.993, 34.08016, 34.08016, 156.2931, 215.8426, 84.05269, 71.36181, 64.52826, 60.62337, 130.9113, 199.2469, 54.76604, 51.83737, 45.00382,  44.0276, 41.09894, 40.12271,  75.2667, 31.33672, 29.38427, 28.40805, 27.43183, 27.43183, 26.45561, 25.47939, 25.47939, 25.47939, 53.78982, 23.52694, 597.5453,  21.5745,  21.5745,  21.5745, 908.9298,   386.69, 1589.101, 716.7693, 194.2357, 116.9664, 135.3179, 259.7441, 126.0452, 548.5397, 320.8293, 62.08268, 194.7711, 410.1355, 195.8638, 125.7385, 303.8485, 156.8094,  72.6489, 108.8429, 61.26662, 782.0512, 252.9391, 498.9469, 1520.309, 1063.955,  161.904, 1185.214, 700.5631, 256.8766, 149.3198, 743.9268, 389.6823, 43.92569, 1225.745, 323.1957, 293.3224, 102.0463, 113.3393, 153.1839, 75.66586, 1280.858, 110.1551, 105.9301, 363.2304, 1940.826, 157.0595,  835.293,  1029.71, 86.05868, 215.1778, 158.0167, 367.3404, 936.1317, 41.74358, 339.0362, 61.45701, 2858.652, 302.8811, 866.1799, 71.94701, 1006.582, 343.7277, 106.5058, 1228.668, 187.4746, 267.4948, 1198.725, 427.2179,  784.605, 795.2588, 79.51619,  2188.59, 424.7687, 518.5816, 48.90871,   590.16, 101.5125, 502.9212, 965.2011, 82.42178, 796.7985, 39.05588, 101.0754, 885.5307, 182.6511, 1228.668, 224.1776, 1179.167, 502.9976, 402.2237, 149.2502, 70.71417, 95.24968, 544.8294,   855.64, 92.81974, 1649.051, 320.8293, 275.7287, 133.5302, 89.70192, 165.5157, 161.2739,   784.91, 268.4836, 562.2307, 278.1942, 183.1487, 101.3895, 249.6762, 470.6365,  1141.75, 1465.941, 187.0229, 500.1337, 1246.733, 183.6112, 1642.269, 4490.351, 2438.852, 237.7442, 76.51835, 379.7365, 218.7713, 138.7211, 547.5282, 1595.708, 696.6878, 904.9869, 312.9316, 876.6634, 340.9842,  278.697, 664.2233, 1172.385, 809.1953,  726.832,  1610.76, 336.1763, 78.98833, 201.3081, 212.9164, 209.8212,  174.432, 1184.435, 279.6245, 988.5189, 155.4483, 271.4873, 135.7924, 2459.178, 368.0916, 593.0227, 179.3064, 718.8468, 138.4295, 779.0965, 143.0448, 130.8893, 793.6916, 931.8213,  293.561, 2531.425, 400.3959, 747.8835, 913.7743, 499.4494, 383.7547, 232.5437, 299.1038, 189.6997, 416.3849, 2615.946, 1332.242, 1642.721, 219.7475, 288.8906,  713.158, 358.5155, 389.9437, 807.9232, 1221.351, 370.0234, 769.5275, 847.1613,  208.396, 315.9844, 285.8128, 596.1623, 746.1524, 958.4762, 202.2754, 196.2279, 284.1781, 369.2497,   310.62, 497.1452, 532.2889, 655.1275, 739.1614, 423.5084, 636.6202, 425.4792, 674.2712, 464.9906, 200.1117, 155.3169, 833.3552, 419.6653, 452.0158,  233.231, 213.8838, 298.5493, 441.8847, 609.7977, 616.6155, 412.0632, 455.4823, 462.4959, 288.8091, 843.6852, 1299.264, 364.2014, 265.7098, 888.2375, 288.3902, 276.8164,  212.914, 246.3925, 770.3191, 753.6121, 1331.372,  1319.47, 629.8383, 589.9307, 255.2755, 296.6175, 1172.748,  634.124, 1075.581, 342.0132, 1183.461, 594.6167, 809.1326, 307.1204, 302.0609, 449.6354,  627.329, 164.5483, 432.8047, 555.0637, 1085.613, 852.6699, 565.8954, 1001.317, 967.5334, 387.6301, 568.6231, 984.8714, 349.6372, 575.4028,  476.831, 328.4911, 396.4098, 652.6521, 593.6404, 894.3167, 480.3987, 1011.634, 909.9426, 663.7475, 517.5323, 726.5857, 614.3827, 958.2359, 426.3834, 934.0519, 392.3509,  854.339, 728.6211, 420.8993, 1231.484, 351.8367, 538.5987, 566.9434, 507.7329,  336.044,  580.471, 701.3115, 559.3331, 801.1266, 328.4911, 257.8202, 1035.856, 402.8628, 516.4849, 536.0586, 926.4419, 1065.006, 940.5381, 359.4894, 380.6479, 884.7072, 543.8793, 662.3917, 548.5397, 373.9489, 385.7864, 554.2819, 378.3353, 506.5577, 419.6016, 534.9739, 389.9437, 427.6708, 570.0417, 773.2256, 454.3367, 957.3751, 265.6299, 478.2004, 471.9902, 358.0207, 679.2488, 639.9905, 370.5964, 426.0436, 526.2531, 380.2701, 459.8489, 468.0925, 292.2401, 711.2732, 419.2825, 409.7844, 374.4659,  377.368, 935.0902, 399.3167, 440.9829, 260.3172, 769.4075, 365.2046, 430.5887, 297.0769, 670.5792, 436.6681, 531.9862, 487.0785, 311.5874, 480.7148, 508.7342, 412.0834, 438.9641, 391.2724, 302.7264, 349.7357, 374.9174, 343.8116,  388.475, 390.5959, 408.1875, 300.9464, 339.9278, 461.2614, 283.5339, 329.3966, 350.6082, 615.3516, 324.5539, 227.5573, 377.7503, 381.8751, 399.4219, 225.6048, 319.7113, 381.8751, 282.5665 ],
"Total": [     7052,     3418,     2258,     4055,     2885,     1796,     3846,     1968,     1522,     1441,     1828,     4082,     5620,     2552,     3404,     5512,     1653,     2035,     4069,     2196,     1586,     2403,     1180,     1347,     2729,     1482,     1308,     4153,     2015,     1215, 1308.895, 1968.718, 689.7644, 517.2993, 383.5904, 1249.806, 348.7099, 308.0159, 290.5756, 249.8816,  245.037, 239.2236, 232.4413, 208.2186,  163.649, 131.6751, 128.7684, 284.7618, 115.2038, 87.10551,  85.1677, 82.26098, 75.47865, 74.50974, 73.54084, 72.57193, 69.66522, 323.5285, 63.85179, 545.3868, 633.5153, 501.1917, 361.1411, 261.6568, 124.5038, 122.5721, 205.6397, 90.69852, 88.76679, 82.00572, 78.14226, 67.51773, 61.72253, 61.72253, 60.75667, 54.96147, 119.6776, 53.02974, 50.13214, 46.26867, 44.33694, 97.46108, 43.37107, 43.37107, 96.49521, 140.9277, 37.57588, 35.64414, 30.81481, 28.88308, 162.6681, 160.7304, 139.4161, 129.7277,  90.0056, 82.25493,  81.2861,  81.2861,  81.2861, 80.31727, 79.34843, 79.34843, 79.34843, 79.34843, 51.25228,  1215.83, 106.4759,  105.504, 1029.907, 87.10121, 79.34696, 33.81328, 30.90678, 30.90678, 30.90678, 140.3903, 60.93764, 24.12495, 23.15612, 22.18729, 576.4472, 407.8446, 371.9924,  290.598, 271.2184, 246.0249, 522.1893, 226.6453, 420.4433, 157.8477, 154.9408,  147.189, 138.4681, 135.5612, 125.8714, 111.3367, 667.5512, 108.4298, 107.4608, 236.3347, 103.5849, 100.6779, 97.77097, 95.83301, 85.17423, 83.23627, 79.36035, 78.39137, 77.42239, 70.63953, 175.2081, 119.0334, 104.5055, 101.5999, 97.72581, 96.75729, 89.97759, 81.26083,  73.5126, 229.4611, 62.85879, 50.26792, 45.42527, 100.6318, 44.45674, 41.55116, 40.58263, 38.64557, 38.64557, 33.80293,  32.8344, 311.7884, 31.86587, 30.89735, 30.89735, 29.92882, 29.92882, 142.3012, 28.96029, 28.96029,  230.728, 89.50352, 84.63371, 83.65975, 57.36277, 359.2658, 42.75333, 39.83145, 38.85749,  35.9356, 33.01371, 29.11786, 29.11786, 26.19598, 25.22201, 25.22201, 22.30013, 22.30013, 22.30013, 22.30013, 21.32617, 19.37824, 17.43032, 17.43032, 15.48239, 15.48239,  71.9509, 33.98107, 33.00562, 14.50843, 192.4107,  182.737, 172.0961, 166.2919,  102.446, 90.83764, 82.13138, 72.45776,  71.4904, 54.07788, 53.11052, 50.20843, 50.20843, 46.33898, 44.40426, 88.90142, 39.56745, 85.03197, 82.12989, 34.73064, 34.73064, 206.9344, 33.76327, 28.92646,  27.9591,  163.423, 26.99174, 26.99174, 24.08965, 24.08965,  1796.15, 1522.343, 461.1008, 419.3502, 400.9022, 297.0111, 288.2726, 286.3307, 1441.739, 198.9457, 593.1445, 292.1544, 108.6478, 87.28705, 64.95532, 57.18776, 53.30398, 52.33303, 48.44926, 47.47831, 45.53642, 44.56548, 44.56548, 43.59453, 42.62359,  40.6817, 38.73981, 37.76886, 34.85603, 34.85603, 157.0684, 217.5889, 84.82803, 72.13715,  65.3036, 61.39871, 132.6576, 201.9539, 55.54138, 52.61271, 45.77916, 44.80294, 41.87427, 40.89805,   77.016, 32.11206, 30.15961, 29.18339, 28.20717, 28.20717, 27.23095, 26.25473, 26.25473, 26.25473, 55.53399, 24.30228, 617.6973, 22.34984, 22.34984, 22.34984, 922.3282, 395.2686, 1653.171, 740.8484, 199.8489, 120.6484, 139.9683, 271.1782,  132.665, 558.9789, 327.4109, 63.83275,  203.304, 437.2617, 208.2656, 133.2959, 318.1883, 163.3808, 75.37757, 112.5474,  63.0187,   818.85, 265.3367,  531.863, 1586.972, 1110.471, 165.5857, 1282.874, 758.3739, 263.4509, 152.0438, 799.1124, 424.3721, 46.64315, 1347.625, 349.1616, 309.5968, 105.7277, 119.9332, 156.8728, 79.34887, 1482.734, 119.6399,  110.577, 394.0429, 2258.139, 161.7071, 924.5173, 1165.312, 89.74789, 235.2712,  171.349, 388.3996, 1030.871, 43.48705, 389.2089, 66.09604, 3418.801, 336.4968, 987.0906,  74.6576, 1180.723,   389.99, 115.9957, 1386.423, 202.7743, 302.1363, 1377.179, 495.8227, 942.8173, 958.3808, 85.17341, 2885.978, 496.2698, 597.8358, 51.62594, 658.8068, 107.1316, 594.6293, 1105.793, 89.01373, 1006.388, 41.77334, 107.6899, 1099.588, 207.6809, 1447.728, 252.0794, 1475.193, 568.7014, 447.6632, 170.3125, 76.33847, 101.8394, 691.9093, 1002.719, 98.44028,  2196.44, 353.4816, 346.2392, 157.6113, 103.0691, 191.4044,  181.428, 936.8471, 288.6252,  707.385, 306.1382, 216.8429, 119.6053, 302.0633,  622.536, 1575.162,   2015.3, 223.6807, 651.0919, 1828.314, 210.5063, 2403.767, 7052.302, 4055.365,  314.108, 83.11828, 481.2863, 269.8495, 162.7376, 642.9535, 2423.736,  924.159, 1255.036, 413.3363, 1382.516,  485.107, 357.8299, 927.4971,  1757.23, 1058.533,  936.876, 2729.834,  458.229,  92.4495, 249.6478, 267.9555, 255.2671, 216.0815, 2118.932, 400.0364, 1553.861, 181.4111, 363.3064, 164.6657, 3846.009, 489.0646, 831.5581, 239.2264, 1153.667,  166.253, 997.9594,  163.208, 144.2563,   1111.6, 1554.677, 403.8165, 5620.605, 632.7189, 1244.021, 1208.139,  725.968, 524.1352, 308.0065, 449.9948, 246.7436, 600.3693, 5512.006, 2473.727, 3404.026, 300.2871, 389.4249, 1190.739, 580.7657, 595.8927, 1384.204, 2552.311,  533.724, 1497.997, 1531.804, 263.3536, 392.3295, 414.3132, 1111.999, 1478.767, 2035.713, 267.7647, 249.2017, 429.1196, 418.7239, 463.6746, 616.3972, 905.2126,  1012.68, 1455.589, 501.8656, 1130.491, 586.1011, 1302.987, 817.7273, 265.7372, 207.6905, 1246.117, 587.1436, 831.6127, 335.6275, 301.6548, 445.6536, 761.6386, 1260.811, 1290.907, 790.7672, 554.8385, 892.3894, 435.5507, 2127.762, 3898.327, 624.7201, 385.6785, 2289.413, 471.3574, 428.6215, 339.5712, 346.8563, 1773.904, 1862.516, 2668.769,  4069.53,   1361.1,  1373.48, 404.2273, 458.1993, 3846.009, 1540.587, 2035.713, 568.5445, 4082.377, 1640.734, 1347.716, 558.2189, 519.8679, 899.9603, 1640.734, 218.4472, 865.0492, 1526.919, 4055.365, 2611.328, 1354.325, 4082.377, 4082.377, 739.4765, 1627.871, 4153.636, 664.3446, 1666.252, 1134.932, 565.6804, 592.8901, 1903.862, 2017.518, 4153.636, 1436.885,  2306.28, 3404.026,  1888.49, 946.2722, 2611.328,   980.49, 3898.327, 925.4418, 3898.327, 959.1622,  4069.53, 2473.727, 1058.858, 7052.302, 492.1751,  1759.76,  1571.76, 1903.862, 713.5364, 900.7551,  3115.53, 1709.537,  4069.53, 592.8034, 542.4112,  3115.53, 913.9105, 1384.204, 1845.483,  4069.53, 5512.006, 7052.302, 697.5651,  826.316, 2552.311, 1949.708, 2986.884, 1520.329, 965.2872, 825.4311, 2017.518, 1374.232, 1646.113, 1009.923, 1666.252,  1757.23,  2306.28,  3115.53, 5620.605, 2059.934, 4153.636, 720.1588, 1828.314, 1238.411, 1524.159, 4082.377, 4153.636, 1862.516, 1415.077, 1845.483, 2059.934,  1888.49,  2306.28, 923.5906, 1909.772, 1455.589, 1949.708, 2289.413, 2423.736, 5620.605, 816.2582, 1280.751, 641.1197, 2986.884, 5620.605, 1436.885,  1373.48,  1826.17, 2668.769, 3404.026,  3115.53, 1796.378, 5512.006, 2668.769, 1246.117, 5620.605, 1666.252, 5512.006, 2611.328, 5512.006, 1796.378, 7052.302, 882.9904, 1709.537, 4055.365, 1773.904, 1520.329,  1888.49, 2017.518, 2986.884, 1646.113, 1524.159, 1434.173, 1434.173, 1374.232, 1293.407, 1238.411, 1295.909, 1553.861,  1826.17 ],
"Category": [ "Default", "Default", "Default", "Default", "Default", "Default", "Default", "Default", "Default", "Default", "Default", "Default", "Default", "Default", "Default", "Default", "Default", "Default", "Default", "Default", "Default", "Default", "Default", "Default", "Default", "Default", "Default", "Default", "Default", "Default", "Topic1", "Topic1", "Topic1", "Topic1", "Topic1", "Topic1", "Topic1", "Topic1", "Topic1", "Topic1", "Topic1", "Topic1", "Topic1", "Topic1", "Topic1", "Topic1", "Topic1", "Topic1", "Topic1", "Topic1", "Topic1", "Topic1", "Topic1", "Topic1", "Topic1", "Topic1", "Topic1", "Topic1", "Topic1", "Topic1", "Topic2", "Topic2", "Topic2", "Topic2", "Topic2", "Topic2", "Topic2", "Topic2", "Topic2", "Topic2", "Topic2", "Topic2", "Topic2", "Topic2", "Topic2", "Topic2", "Topic2", "Topic2", "Topic2", "Topic2", "Topic2", "Topic2", "Topic2", "Topic2", "Topic2", "Topic2", "Topic2", "Topic2", "Topic2", "Topic2", "Topic3", "Topic3", "Topic3", "Topic3", "Topic3", "Topic3", "Topic3", "Topic3", "Topic3", "Topic3", "Topic3", "Topic3", "Topic3", "Topic3", "Topic3", "Topic3", "Topic3", "Topic3", "Topic3", "Topic3", "Topic3", "Topic3", "Topic3", "Topic3", "Topic3", "Topic3", "Topic3", "Topic3", "Topic3", "Topic3", "Topic4", "Topic4", "Topic4", "Topic4", "Topic4", "Topic4", "Topic4", "Topic4", "Topic4", "Topic4", "Topic4", "Topic4", "Topic4", "Topic4", "Topic4", "Topic4", "Topic4", "Topic4", "Topic4", "Topic4", "Topic4", "Topic4", "Topic4", "Topic4", "Topic4", "Topic4", "Topic4", "Topic4", "Topic4", "Topic4", "Topic5", "Topic5", "Topic5", "Topic5", "Topic5", "Topic5", "Topic5", "Topic5", "Topic5", "Topic5", "Topic5", "Topic5", "Topic5", "Topic5", "Topic5", "Topic5", "Topic5", "Topic5", "Topic5", "Topic5", "Topic5", "Topic5", "Topic5", "Topic5", "Topic5", "Topic5", "Topic5", "Topic5", "Topic5", "Topic5", "Topic6", "Topic6", "Topic6", "Topic6", "Topic6", "Topic6", "Topic6", "Topic6", "Topic6", "Topic6", "Topic6", "Topic6", "Topic6", "Topic6", "Topic6", "Topic6", "Topic6", "Topic6", "Topic6", "Topic6", "Topic6", "Topic6", "Topic6", "Topic6", "Topic6", "Topic6", "Topic6", "Topic6", "Topic6", "Topic6", "Topic7", "Topic7", "Topic7", "Topic7", "Topic7", "Topic7", "Topic7", "Topic7", "Topic7", "Topic7", "Topic7", "Topic7", "Topic7", "Topic7", "Topic7", "Topic7", "Topic7", "Topic7", "Topic7", "Topic7", "Topic7", "Topic7", "Topic7", "Topic7", "Topic7", "Topic7", "Topic7", "Topic7", "Topic7", "Topic7", "Topic8", "Topic8", "Topic8", "Topic8", "Topic8", "Topic8", "Topic8", "Topic8", "Topic8", "Topic8", "Topic8", "Topic8", "Topic8", "Topic8", "Topic8", "Topic8", "Topic8", "Topic8", "Topic8", "Topic8", "Topic8", "Topic8", "Topic8", "Topic8", "Topic8", "Topic8", "Topic8", "Topic8", "Topic8", "Topic8", "Topic9", "Topic9", "Topic9", "Topic9", "Topic9", "Topic9", "Topic9", "Topic9", "Topic9", "Topic9", "Topic9", "Topic9", "Topic9", "Topic9", "Topic9", "Topic9", "Topic9", "Topic9", "Topic9", "Topic9", "Topic9", "Topic9", "Topic9", "Topic9", "Topic9", "Topic9", "Topic9", "Topic9", "Topic9", "Topic9", "Topic1", "Topic1", "Topic1", "Topic2", "Topic2", "Topic2", "Topic2", "Topic3", "Topic3", "Topic4", "Topic4", "Topic5", "Topic5", "Topic6", "Topic6", "Topic6", "Topic7", "Topic7", "Topic7", "Topic8", "Topic8", "Topic9", "Topic9", "Topic9", "Topic1", "Topic1", "Topic1", "Topic2", "Topic3", "Topic4", "Topic4", "Topic5", "Topic6", "Topic6", "Topic7", "Topic7", "Topic8", "Topic8", "Topic9", "Topic1", "Topic3", "Topic6", "Topic6", "Topic8", "Topic8", "Topic9", "Topic1", "Topic1", "Topic2", "Topic2", "Topic3", "Topic3", "Topic4", "Topic4", "Topic5", "Topic6", "Topic6", "Topic7", "Topic7", "Topic8", "Topic8", "Topic9", "Topic9", "Topic9", "Topic1", "Topic2", "Topic3", "Topic4", "Topic5", "Topic5", "Topic5", "Topic5", "Topic6", "Topic7", "Topic8", "Topic9", "Topic1", "Topic2", "Topic3", "Topic4", "Topic5", "Topic6", "Topic6", "Topic8", "Topic9", "Topic9", "Topic1", "Topic2", "Topic3", "Topic4", "Topic4", "Topic5", "Topic7", "Topic8", "Topic9", "Topic1", "Topic2", "Topic3", "Topic4", "Topic6", "Topic6", "Topic6", "Topic7", "Topic8", "Topic1", "Topic1", "Topic2", "Topic4", "Topic5", "Topic6", "Topic7", "Topic9", "Topic2", "Topic3", "Topic5", "Topic8", "Topic9", "Topic2", "Topic3", "Topic4", "Topic5", "Topic6", "Topic7", "Topic8", "Topic9", "Topic9", "Topic1", "Topic2", "Topic3", "Topic3", "Topic5", "Topic6", "Topic6", "Topic7", "Topic8", "Topic3", "Topic4", "Topic4", "Topic5", "Topic5", "Topic6", "Topic7", "Topic7", "Topic8", "Topic5", "Topic6", "Topic6", "Topic8", "Topic8", "Topic9", "Topic9", "Topic1", "Topic2", "Topic3", "Topic6", "Topic7", "Topic7", "Topic1", "Topic2", "Topic3", "Topic4", "Topic5", "Topic5", "Topic6", "Topic6", "Topic9", "Topic1", "Topic2", "Topic3", "Topic5", "Topic6", "Topic7", "Topic2", "Topic3", "Topic3", "Topic5", "Topic9", "Topic2", "Topic3", "Topic6", "Topic7", "Topic8", "Topic9", "Topic2", "Topic6", "Topic2", "Topic3", "Topic4", "Topic5", "Topic6", "Topic6", "Topic6", "Topic7", "Topic8", "Topic9", "Topic1", "Topic7", "Topic1", "Topic2", "Topic4", "Topic7", "Topic1", "Topic3", "Topic4", "Topic2", "Topic5", "Topic8", "Topic9", "Topic1", "Topic4", "Topic6", "Topic7", "Topic7", "Topic2", "Topic3", "Topic6", "Topic6", "Topic9", "Topic1", "Topic7", "Topic3", "Topic5", "Topic7", "Topic8", "Topic2", "Topic5", "Topic6", "Topic8", "Topic9", "Topic2", "Topic3", "Topic5", "Topic1", "Topic2", "Topic3", "Topic5", "Topic6", "Topic2", "Topic6", "Topic8", "Topic1", "Topic2", "Topic6", "Topic9", "Topic1", "Topic5", "Topic8", "Topic3", "Topic6", "Topic7", "Topic2", "Topic5", "Topic8", "Topic3", "Topic3", "Topic7", "Topic9", "Topic3", "Topic5", "Topic7", "Topic8", "Topic5", "Topic8", "Topic2", "Topic4", "Topic6", "Topic9", "Topic9", "Topic9", "Topic1", "Topic2", "Topic3", "Topic4", "Topic7", "Topic1", "Topic2", "Topic3", "Topic3", "Topic5", "Topic5", "Topic6", "Topic7", "Topic3", "Topic4", "Topic5", "Topic6", "Topic9", "Topic8", "Topic1", "Topic5", "Topic2", "Topic8", "Topic2", "Topic9", "Topic1", "Topic2", "Topic3", "Topic8", "Topic4", "Topic4", "Topic5", "Topic6", "Topic2", "Topic1", "Topic2", "Topic6", "Topic4", "Topic5", "Topic6", "Topic6", "Topic7", "Topic6", "Topic3", "Topic4", "Topic7", "Topic7", "Topic8", "Topic3", "Topic5", "Topic1", "Topic9", "Topic2", "Topic4", "Topic7", "Topic3", "Topic6", "Topic7", "Topic2", "Topic4", "Topic7", "Topic2", "Topic8", "Topic7", "Topic1", "Topic2", "Topic5", "Topic7", "Topic7", "Topic1", "Topic4", "Topic4", "Topic7", "Topic1", "Topic9", "Topic6", "Topic7", "Topic1", "Topic2", "Topic3", "Topic6", "Topic7", "Topic8", "Topic3", "Topic6", "Topic8", "Topic2", "Topic9", "Topic5", "Topic5", "Topic8", "Topic8", "Topic4", "Topic6", "Topic7", "Topic8", "Topic3", "Topic7", "Topic5", "Topic8", "Topic1", "Topic5", "Topic9", "Topic2", "Topic4", "Topic6", "Topic9", "Topic5", "Topic4", "Topic7" ] 
},
"token.table": {
 "Term": [ "103-1", "103-2", "103-3", "access", "access", "access", "access", "access", "accid", "accord", "accord", "accord", "accord", "accord", "accord", "accord", "account", "account", "account", "account", "account", "account", "account", "accru", "accumul", "accumul", "across", "across", "across", "across", "action", "action", "action", "action", "action", "action", "action", "activ", "activ", "activ", "activ", "activ", "activ", "activ", "actuari", "adequ", "adequ", "age", "age", "age", "age", "age", "agement", "agm", "agricultur", "agricultur", "air", "air", "amfori", "amort", "amortis", "amount", "amount", "amount", "amount", "anim", "anim", "annual", "annual", "annual", "annual", "annual", "annual", "annual", "appetit", "applic", "applic", "applic", "applic", "applic", "applic", "applic", "appoint", "appoint", "appoint", "apprentic", "apprentic", "apprenticeship", "apprenticeship", "approach", "approach", "approach", "approach", "approach", "approach", "appropri", "appropri", "appropri", "appropri", "appropri", "appropri", "area", "area", "area", "area", "area", "area", "area", "asda", "asko", "asko", "assess", "assess", "assess", "asset", "asset", "associ", "associ", "associ", "associ", "associ", "associ", "associ", "associ", "assur", "assur", "audit", "audit", "audit", "audit", "auditor", "auditor", "auditor", "autom", "autom", "autom", "axel", "bag", "bag", "bag", "bangladesh", "baselin", "baselin", "baselin", "basi", "basi", "basi", "basi", "basi", "basi", "basi", "basi", "bed", "beef", "ben", "benefit", "benefit", "benefit", "benefit", "benefit", "bepi", "better", "better", "better", "better", "better", "big", "big", "bio-planet", "bioga", "bnok", "board", "board", "boss", "bottl", "brand", "brand", "brand", "brand", "brand", "breach", "breast", "bsci", "campaign", "campaign", "campaign", "cancer", "capit", "capit", "capit", "capit", "carbon", "career", "career", "career", "carrefour", "cash", "cash", "cater", "cdp", "ceo", "ceo", "ceo", "ceo", "ceo", "certif", "certif", "certif", "certif", "certif", "certif", "certifi", "certifi", "cfo", "cfo", "chain", "chain", "chain", "chain", "chair", "chair", "chairman", "chairman", "champion", "chang", "chang", "chang", "chang", "chang", "chang", "charit", "chariti", "chief", "chief", "chief", "chief", "child", "child", "children", "clarifi", "climat", "climat", "climat", "climat", "climat", "climat", "cms", "co-oper", "co2", "co2", "co2e", "cocoa", "code", "code", "code", "code", "coffe", "coffe", "coffe", "colleagu", "commit", "commit", "commit", "commit", "commit", "commit", "committe", "committe", "communiti", "communiti", "compact", "compact", "compani", "compani", "compani", "compani", "compani", "compani", "compani", "compani", "compens", "compens", "compens", "compens", "complianc", "complianc", "complianc", "complianc", "concept", "concept", "concept", "concept", "concept", "concern", "concern", "concern", "concern", "concern", "confidenti", "consolid", "consolid", "consum", "consum", "consum", "consum", "consumpt", "consumpt", "consumpt", "consumpt", "continu", "continu", "continu", "continu", "continu", "continu", "continu", "continu", "continu", "control", "control", "control", "control", "control", "control", "conveni", "conveni", "conveni", "cool", "cool", "coronavirus", "coronavirus", "coronavirus", "corpor", "corpor", "corpor", "corpor", "corpor", "corpor", "cost", "cost", "cost", "cost", "cost", "cotton", "countri", "countri", "countri", "countri", "countri", "countri", "cours", "cours", "cours", "cours", "cours", "covid-19", "covid-19", "covid-19", "covid-19", "covid-19", "creat", "creat", "creat", "creat", "creat", "creat", "creat", "creat", "creat", "creativ", "cru", "currenc", "cus-", "custom", "custom", "custom", "custom", "custom", "custom", "dairi", "dairi", "data", "data", "data", "data", "debt", "deduct", "defer", "defer", "defici", "del", "del", "deli", "deliveri", "deliveri", "deliveri", "deliveri", "deliveri", "deliveri", "deloitt", "demand", "demand", "demand", "demand", "demand", "depreci", "deputi", "descript", "descript", "descript", "descript", "develop", "develop", "develop", "develop", "develop", "develop", "develop", "develop", "develop", "deviat", "deviat", "deviat", "dialog", "dialog", "diesel", "dilig", "dilig", "dilut", "dioxid", "director", "director", "director", "directorship", "disabl", "disabl", "disabl", "disadvantag", "discrep", "divers", "divers", "divers", "divers", "divers", "dnv", "doctor", "document", "document", "document", "donat", "donat", "dreamland", "e-commerc", "e-commerc", "e-learn", "eat", "eat", "eat", "eat", "edingensesteenweg", "effici", "effici", "effici", "effici", "effici", "effici", "egg", "elect", "elect", "elect", "electr", "electr", "emiss", "employ", "employ", "employ", "employ", "employe", "employe", "employe", "employe", "employe", "employe", "end", "end", "end", "end", "end", "end", "end", "end", "end", "energi", "energi", "energi", "english", "english", "enseign", "enseign", "environ", "environ", "environ", "environ", "environ", "environ", "environ", "environment", "environment", "environment", "equal", "equal", "equal", "equal", "equiti", "equiti", "ergonom", "error", "euro", "euro", "euro", "everyon", "everyon", "everyon", "evid", "evid", "evid", "execut", "execut", "execut", "expens", "explor", "factori", "factori", "factori", "failur", "failur", "fairer", "fairtrad", "fairtrad", "famili", "famili", "famili", "famili", "famili", "fareshar", "farm", "farm", "farm", "farm", "farm", "farmer", "farmer", "farmer", "fat", "feel", "feel", "femal", "financi", "financi", "financi", "financi", "financi", "financi", "fish", "fisheri", "fleet", "fleet", "flow", "flow", "flow", "flow", "flower", "food", "food", "food", "food", "food", "food", "food", "foodservic", "foodservic", "footprint", "footprint", "footprint", "footprint", "förbund", "format", "format", "format", "format", "format", "format", "format", "fossil", "foundat", "foundat", "foundat", "foundat", "foundat", "foundat", "fran", "fraud", "fresh", "fresh", "fresh", "fruit", "fruit", "fruit", "fsc", "fuel", "fuel", "fuel", "fuel", "fund", "fund", "fund", "fundrais", "gas", "gase", "gender", "gender", "general", "general", "general", "general", "general", "general", "get", "get", "ghg", "global", "global", "global", "global", "global", "global", "goal", "goal", "goal", "goal", "goal", "goal", "goal", "goal", "good", "good", "good", "good", "good", "good", "good", "good", "good", "goodwil", "govern", "govern", "govern", "govern", "govern", "govern", "govern", "govern", "graduat", "grant", "grant", "grant", "grant", "grc", "greenhous", "gri", "gri", "grievanc", "gro", "groceri", "groceri", "group", "group", "group", "group", "group", "group", "group", "group", "group", "growth", "growth", "growth", "gwh", "halv", "head", "head", "head", "head", "head", "head", "health", "health", "health", "health", "healthi", "healthi", "healthi", "healthi", "healthier", "healthier", "heat", "hedg", "help", "help", "help", "help", "help", "help", "hemköp", "hereinaft", "high-risk", "high-risk", "hire", "hire", "holt", "home", "home", "home", "home", "hour", "hour", "hour", "hour", "hour", "human", "human", "hunger", "husbandri", "hydrogen", "hydrogen", "ia", "ie", "ifr", "ill", "ilo", "impact", "impact", "impact", "impact", "impact", "impact", "impair", "implement", "implement", "implement", "implement", "implement", "implement", "implement", "includ", "includ", "includ", "includ", "includ", "includ", "includ", "includ", "includ", "incom", "incom", "incom", "incom", "increas", "increas", "increas", "increas", "increas", "increas", "increas", "incur", "inform", "inform", "inform", "inform", "inform", "inform", "inform", "inform", "inher", "initi", "initi", "initi", "initi", "initi", "initi", "injuri", "instal", "instal", "instal", "instal", "instrument", "instrument", "instrument", "intang", "interest", "interest", "interest", "interest", "interest", "interest-bear", "intern", "intern", "intern", "intern", "intern", "intern", "internship", "invest", "invest", "invest", "invest", "invest", "invest", "invest", "ireland", "ireland", "irish", "iro", "isa", "jan", "jef", "job", "job", "joker", "juic", "k-food", "kevin", "kiwi", "knight", "know", "know", "know", "kori", "kori", "kpmg", "kwh", "label", "label", "label", "label", "labor", "labor", "labour", "labour", "labour", "landfil", "launder", "law", "law", "law", "leas", "leas", "leav", "leav", "legisl", "legisl", "liabil", "lifestyl", "lifestyl", "light", "light", "light", "light", "littl", "littl", "live", "live", "live", "live", "loan", "local", "local", "local", "local", "local", "local", "log", "log", "log", "logist", "logist", "logist", "logist", "logist", "logist", "loss", "loss", "loss", "loss", "loss", "loss", "loss", "low-carbon", "ltip", "madrid", "make", "make", "make", "make", "make", "make", "make", "make", "manag", "manag", "manag", "manag", "manag", "manag", "manage-", "market", "market", "market", "market", "market", "market", "materi", "materi", "materi", "materi", "materi", "materi", "matter", "matter", "matter", "matter", "matter", "matter", "measur", "measur", "measur", "measur", "measur", "measur", "measur", "measur", "meat", "meet", "meet", "meet", "meet", "meet", "meet", "meet", "meet", "meet", "member", "member", "member", "member", "men", "meni", "mercadona", "messag", "messag", "migrant", "milk", "misstat", "mmu", "mnok", "mnok", "mploy", "multi-stakehold", "mwh", "natali", "need", "need", "need", "need", "need", "need", "neighborhood", "neighbourhood", "neighbourhood", "net", "net", "net", "net", "nhs", "nit", "nme", "nme", "nomin", "nomin", "nomin", "non-control", "non-curr", "non-government", "norgesgruppen", "norway", "norwegian", "note", "note", "note", "note", "note", "note", "number", "number", "number", "number", "number", "number", "number", "number", "number", "obtain", "obtain", "obtain", "obtain", "obtain", "obtain", "occup", "occup", "offer", "offer", "offer", "offer", "offic", "offic", "offic", "offic", "offic", "offic", "offic", "oil", "oil", "okay", "omnichannel", "onlin", "onlin", "onlin", "onlin", "ontent", "oper", "oper", "oper", "oper", "oper", "oper", "oper", "oper", "opinion", "opportun", "opportun", "opportun", "opportun", "opportun", "organ", "organ", "organ", "organ", "organ", "organ", "organ", "organ", "osuuskauppa", "overse", "overse", "own-brand", "own-brand", "packag", "packag", "packag", "palm", "pandem", "pandem", "pandem", "pandem", "pandem", "paper", "paper", "paper", "paper", "partnership", "partnership", "partnership", "payabl", "pension", "pension", "pension", "peopl", "peopl", "peopl", "peopl", "peopl", "perform", "perform", "perform", "perform", "perform", "perform", "perform", "perform", "personnel", "personnel", "personnel", "personnel", "personnel", "pesticid", "peter", "peter", "photovolta", "pick-up", "plan", "plan", "plan", "plan", "plan", "plan", "plan", "plastic", "plastic", "polici", "polici", "polici", "polici", "polici", "polici", "polici", "polit", "polit", "popular", "portug", "portug", "portug", "postpon", "poultri", "poverti", "poverti", "ppli", "prepar", "prepar", "prepar", "prepar", "prepar", "prepar", "presid", "presid", "presid", "price", "price", "price", "price", "price", "price", "principl", "principl", "principl", "principl", "principl", "privaci", "privaci", "privaci", "privat", "privat", "privat", "privat", "privat", "privat", "procedur", "procedur", "procedur", "process", "process", "process", "process", "process", "process", "produc", "produc", "produc", "produc", "product", "product", "product", "product", "product", "profit", "profit", "profit", "project", "project", "project", "project", "project", "project", "promot", "promot", "promot", "promot", "promot", "properti", "properti", "properti", "properti", "propos", "propos", "propos", "propos", "protect", "protect", "protect", "protect", "protect", "proud", "provid", "provid", "provid", "provid", "provid", "provid", "provid", "provid", "provid", "provis", "provis", "provis", "provis", "provis", "provis", "provis", "publ", "rainwat", "rang", "rang", "rang", "rang", "rang", "rate", "rate", "rate", "rate", "reappoint", "receiv", "receiv", "receiv", "receiv", "receiv", "receiv", "receiv", "recover", "recoveri", "recoveri", "recoveri", "recoveri", "recruit", "recruit", "recruit", "recycl", "recycl", "reduc", "reduc", "reduc", "reduc", "reduc", "reduct", "reduct", "reduct", "reduct", "refriger", "regard", "regard", "regard", "regard", "regard", "regard", "region", "region", "region", "region", "region", "region", "regul", "regul", "regul", "regul", "regul", "regul", "regulatori", "regulatori", "regulatori", "regulatori", "regulatori", "rehabilit", "relat", "relat", "relat", "relat", "relat", "relat", "remuner", "remuner", "renew", "renew", "renew", "renew", "report", "report", "report", "report", "report", "report", "report", "repres", "repres", "repres", "repres", "repres", "repres", "repres", "repres", "requir", "requir", "requir", "requir", "requir", "requir", "requir", "reserv", "reserv", "reserv", "reserv", "resourc", "resourc", "resourc", "resourc", "resourc", "resourc", "respons", "respons", "respons", "respons", "respons", "respons", "restaur", "restaur", "restaur", "result", "result", "result", "result", "result", "result", "result", "result", "result", "retail", "retail", "retail", "retail", "retail", "retail", "retail", "retail", "retail", "retailer-own", "reusabl", "review", "review", "review", "review", "review", "review", "review", "review", "right", "right", "right", "right", "right-of-us", "risk", "risk", "risk", "risk", "roc", "roig", "roof", "rspo", "s-bank", "safeti", "safeti", "safeti", "safeti", "safeti", "salari", "salari", "salari", "salari", "sale", "sale", "sale", "sale", "sale", "sale", "salt", "sampl", "sampl", "say", "say", "say", "school", "school", "school", "school", "scope", "scope", "scope", "scope", "sdg", "sdg", "sdg", "seafood", "seminar", "senior", "senior", "servic", "servic", "servic", "servic", "servic", "servic", "servic", "servic", "servic", "sexual", "share", "share", "share", "share", "share", "share", "share", "sharehold", "sharehold", "sheet", "sheet", "sheet", "shop", "shop", "short-term", "short-term", "short-term", "sinc", "sinc", "sinc", "sinc", "sinc", "sinc", "sinc", "skill", "skill", "smes", "social", "social", "social", "social", "sok", "sok", "solar", "soluci", "sourc", "sourc", "sourc", "sourc", "sourc", "sourc", "sourc", "sourc", "southwest", "soy", "spar", "speci", "spt", "stakehold", "stakehold", "stakehold", "standard", "standard", "standard", "standard", "standard", "statement", "statement", "statement", "statut", "sto", "sto", "store", "store", "store", "store", "store", "storekeep", "strategi", "strategi", "strategi", "strategi", "strategi", "strategi", "strategi", "strong", "strong", "strong", "strong", "strong", "strong", "suffici", "suffici", "suffici", "suffici", "suffici", "sugar", "sugar", "supercor", "supermarket", "supermarket", "supermarket", "supermarket", "supermarket", "supervisori", "supervisori", "suppli", "suppli", "suppli", "suppli", "supplier", "supplier", "supplier", "supplier", "supplier", "supplier", "support", "support", "support", "support", "support", "support", "support", "support", "sure", "sure", "sustain", "sustain", "sustain", "sustain", "sustain", "sustain", "sustain", "sustain", "sustainabilit", "sustainabilit", "system", "system", "system", "system", "system", "system", "tab", "tackl", "talent", "talent", "target", "target", "target", "target", "target", "target", "target", "target", "target", "tax", "tax", "tax", "tax", "tea", "tel", "territori", "territori", "territori", "thailand", "think", "think", "time", "time", "time", "time", "time", "time", "time", "time", "time", "tomer", "tonn", "tonn", "topic", "topic", "total", "total", "total", "total", "total", "total", "total", "train", "train", "traine", "transact", "transact", "transpar", "transpar", "transpar", "transpar", "transpar", "transport", "transport", "transport", "trend", "trend", "trend", "truck", "trumf", "tsr", "tuna", "use", "use", "use", "use", "use", "use", "use", "valencia", "valu", "valu", "valu", "valu", "valu", "valu", "valu", "veget", "veget", "vehicl", "vehicl", "vehicl", "ventur", "ventur", "verif", "vest", "vest", "vice", "vice", "vice", "vice", "voic", "volunt", "vote", "voucher", "wage", "wage", "wage", "want", "want", "want", "want", "want", "want", "warehous", "warehous", "warehous", "warehous", "warehous", "wast", "water", "water", "water", "way", "way", "way", "way", "way", "way", "way", "way", "way", "webshop", "welfar", "welfar", "wellb", "wellb", "whistleblow", "wholesal", "wholesal", "wholesal", "willi", "willi", "wind", "wind", "women", "women", "work", "work", "work", "work", "work", "work", "work", "work", "work-lif", "worker", "worker", "worker", "workforc", "workplac", "workplac", "wouter", "xx.x", "young", "young", "young", "young", "youth", "zero", "zero", "zero", "zero" ],
"Topic": [ 3, 3, 3, 2, 5, 6, 7, 9, 7, 1, 3, 4, 6, 7, 8, 9, 1, 3, 4, 5, 6, 8, 9, 1, 1, 8, 2, 3, 5, 8, 1, 2, 3, 4, 6, 7, 8, 1, 2, 3, 5, 6, 7, 8, 1, 6, 8, 1, 4, 5, 7, 9, 6, 9, 3, 4, 4, 8, 3, 1, 1, 1, 4, 5, 8, 3, 4, 1, 2, 4, 5, 6, 8, 9, 6, 1, 3, 4, 6, 7, 8, 9, 5, 6, 9, 2, 7, 2, 7, 1, 2, 3, 4, 6, 8, 1, 3, 4, 5, 6, 9, 2, 3, 4, 5, 6, 7, 8, 2, 5, 6, 1, 3, 6, 1, 7, 1, 2, 3, 4, 6, 7, 8, 9, 4, 6, 3, 6, 7, 9, 1, 6, 9, 4, 5, 8, 9, 2, 4, 5, 3, 3, 6, 8, 1, 2, 3, 4, 6, 7, 8, 9, 2, 4, 9, 1, 2, 5, 7, 9, 3, 2, 3, 4, 5, 7, 2, 5, 5, 8, 5, 6, 9, 7, 4, 2, 3, 4, 5, 6, 6, 2, 3, 2, 4, 7, 2, 1, 5, 8, 9, 8, 6, 7, 9, 6, 1, 9, 5, 8, 1, 2, 5, 6, 9, 2, 3, 4, 6, 7, 8, 4, 6, 3, 9, 3, 4, 5, 8, 2, 9, 5, 9, 2, 1, 2, 3, 5, 6, 8, 2, 2, 2, 5, 6, 9, 2, 3, 2, 6, 2, 3, 4, 6, 8, 9, 6, 2, 1, 8, 8, 4, 3, 6, 7, 9, 1, 2, 4, 2, 1, 2, 3, 4, 7, 8, 6, 9, 2, 3, 3, 5, 1, 2, 3, 5, 6, 7, 8, 9, 1, 3, 7, 9, 2, 3, 5, 6, 4, 5, 6, 7, 8, 1, 3, 4, 6, 7, 6, 1, 6, 3, 4, 5, 8, 3, 4, 5, 8, 1, 2, 3, 4, 5, 6, 7, 8, 9, 1, 4, 5, 6, 8, 9, 4, 5, 6, 8, 9, 2, 5, 7, 1, 3, 5, 6, 8, 9, 1, 2, 5, 8, 9, 4, 1, 3, 4, 5, 7, 8, 1, 2, 6, 7, 8, 1, 2, 5, 7, 8, 1, 2, 3, 4, 5, 6, 7, 8, 9, 2, 5, 1, 5, 2, 3, 4, 5, 7, 8, 4, 6, 1, 2, 6, 8, 1, 1, 1, 5, 6, 7, 9, 5, 1, 2, 3, 5, 8, 9, 6, 3, 4, 5, 7, 8, 1, 9, 5, 6, 8, 9, 1, 2, 3, 4, 5, 6, 7, 8, 9, 6, 8, 9, 2, 3, 8, 3, 6, 1, 8, 3, 6, 9, 9, 3, 7, 9, 2, 6, 2, 3, 4, 7, 9, 6, 7, 1, 3, 6, 2, 8, 5, 5, 9, 7, 2, 3, 4, 5, 9, 4, 5, 6, 7, 8, 9, 4, 1, 6, 9, 5, 8, 8, 1, 3, 7, 9, 1, 3, 5, 6, 7, 9, 1, 2, 3, 4, 5, 6, 7, 8, 9, 4, 7, 8, 2, 6, 4, 7, 2, 3, 4, 5, 6, 7, 8, 3, 4, 8, 1, 3, 7, 9, 1, 7, 7, 6, 1, 2, 7, 2, 5, 7, 3, 6, 7, 6, 7, 9, 1, 2, 3, 4, 6, 6, 7, 2, 2, 4, 2, 4, 5, 7, 9, 2, 2, 3, 4, 5, 8, 2, 4, 9, 4, 2, 4, 7, 1, 4, 5, 6, 8, 9, 4, 4, 5, 8, 1, 5, 6, 8, 4, 1, 2, 3, 4, 5, 8, 9, 5, 9, 2, 4, 5, 8, 9, 1, 3, 4, 5, 7, 8, 9, 8, 2, 3, 4, 6, 7, 9, 9, 6, 4, 5, 8, 2, 4, 7, 4, 1, 4, 5, 8, 1, 2, 4, 2, 8, 8, 3, 7, 1, 3, 5, 6, 7, 9, 2, 7, 8, 2, 3, 6, 7, 8, 9, 2, 3, 4, 5, 6, 7, 8, 9, 1, 2, 3, 4, 5, 6, 7, 8, 9, 1, 1, 2, 4, 5, 6, 7, 8, 9, 7, 1, 2, 3, 9, 6, 8, 3, 8, 3, 9, 4, 5, 1, 2, 3, 4, 5, 6, 7, 8, 9, 2, 5, 9, 8, 8, 1, 2, 3, 6, 7, 9, 2, 3, 4, 7, 2, 3, 4, 8, 2, 4, 8, 1, 2, 3, 4, 5, 6, 8, 5, 6, 3, 4, 2, 7, 9, 2, 4, 5, 7, 2, 3, 5, 7, 8, 3, 9, 2, 4, 7, 8, 1, 3, 1, 7, 3, 1, 2, 3, 5, 6, 8, 1, 2, 3, 4, 5, 6, 7, 8, 1, 2, 3, 4, 5, 6, 7, 8, 9, 1, 3, 4, 6, 1, 2, 4, 5, 6, 7, 8, 1, 1, 2, 3, 4, 5, 6, 8, 9, 6, 1, 2, 3, 4, 7, 8, 7, 1, 4, 5, 8, 1, 4, 9, 1, 1, 2, 3, 6, 9, 1, 1, 3, 6, 7, 8, 9, 7, 1, 2, 3, 5, 7, 8, 9, 2, 3, 3, 3, 6, 9, 9, 2, 7, 5, 4, 8, 9, 5, 9, 2, 4, 9, 6, 9, 6, 8, 3, 4, 5, 6, 1, 3, 1, 3, 7, 8, 6, 1, 6, 9, 1, 8, 2, 7, 3, 6, 1, 2, 5, 2, 4, 6, 8, 2, 5, 1, 2, 3, 4, 1, 2, 3, 4, 5, 6, 8, 4, 7, 8, 1, 2, 5, 7, 8, 9, 1, 2, 3, 4, 5, 6, 8, 8, 9, 7, 1, 2, 3, 4, 5, 6, 8, 9, 1, 3, 6, 7, 8, 9, 6, 1, 3, 4, 5, 6, 9, 1, 2, 3, 4, 6, 8, 1, 2, 3, 6, 7, 9, 1, 2, 3, 4, 5, 6, 7, 8, 4, 1, 2, 3, 4, 5, 6, 7, 8, 9, 2, 3, 4, 9, 7, 5, 7, 2, 8, 3, 4, 6, 3, 1, 5, 3, 3, 8, 9, 1, 2, 5, 6, 7, 8, 2, 5, 7, 1, 2, 5, 8, 2, 3, 3, 7, 1, 5, 9, 1, 1, 3, 5, 5, 5, 1, 3, 4, 6, 7, 9, 1, 2, 3, 4, 5, 6, 7, 8, 9, 1, 2, 3, 5, 6, 8, 3, 7, 2, 4, 5, 7, 2, 3, 4, 6, 7, 8, 9, 4, 8, 5, 5, 2, 3, 5, 7, 3, 1, 3, 4, 5, 6, 7, 8, 9, 6, 2, 3, 5, 6, 7, 1, 2, 3, 4, 5, 6, 7, 9, 9, 6, 8, 4, 8, 2, 4, 8, 4, 1, 2, 5, 7, 8, 3, 4, 7, 8, 2, 3, 4, 1, 1, 7, 9, 2, 3, 5, 6, 7, 1, 2, 3, 5, 6, 7, 8, 9, 1, 6, 7, 8, 9, 4, 8, 9, 8, 5, 1, 2, 4, 6, 7, 8, 9, 4, 8, 1, 3, 4, 6, 7, 8, 9, 2, 3, 5, 4, 7, 8, 7, 4, 2, 3, 3, 1, 2, 5, 6, 7, 9, 5, 7, 9, 1, 4, 5, 6, 7, 9, 1, 2, 3, 6, 8, 2, 6, 7, 3, 4, 5, 7, 8, 9, 3, 4, 6, 3, 4, 5, 6, 7, 8, 3, 4, 5, 8, 1, 3, 4, 5, 8, 1, 5, 6, 1, 2, 3, 4, 7, 8, 2, 3, 4, 5, 7, 1, 5, 8, 9, 4, 6, 8, 9, 2, 3, 4, 6, 7, 2, 1, 2, 3, 4, 5, 6, 7, 8, 9, 1, 2, 3, 4, 6, 7, 9, 6, 8, 2, 3, 4, 5, 7, 1, 7, 8, 9, 9, 1, 2, 3, 4, 5, 7, 9, 1, 1, 2, 7, 8, 2, 3, 7, 4, 8, 1, 2, 3, 4, 8, 1, 2, 4, 8, 8, 1, 3, 4, 5, 6, 8, 3, 4, 5, 7, 8, 9, 1, 3, 4, 6, 7, 9, 1, 3, 4, 6, 7, 7, 1, 3, 6, 7, 8, 9, 3, 9, 4, 5, 8, 9, 1, 2, 3, 5, 6, 8, 9, 1, 3, 4, 5, 6, 7, 8, 9, 1, 3, 4, 5, 6, 7, 8, 1, 2, 3, 5, 2, 3, 4, 7, 8, 9, 2, 3, 4, 6, 7, 9, 4, 5, 8, 1, 2, 3, 4, 5, 6, 7, 8, 9, 1, 2, 3, 4, 5, 6, 7, 8, 9, 5, 4, 1, 3, 4, 5, 6, 7, 8, 9, 1, 2, 3, 9, 1, 1, 3, 6, 8, 9, 7, 8, 4, 5, 2, 3, 6, 7, 8, 1, 3, 7, 9, 1, 4, 5, 6, 7, 8, 4, 2, 6, 2, 5, 7, 2, 3, 7, 9, 1, 6, 7, 8, 3, 4, 8, 4, 7, 7, 9, 1, 2, 3, 4, 5, 6, 7, 8, 9, 7, 1, 2, 3, 4, 5, 8, 9, 1, 9, 1, 4, 6, 2, 5, 1, 2, 6, 1, 2, 3, 4, 7, 8, 9, 2, 7, 7, 2, 3, 7, 9, 8, 9, 8, 5, 1, 2, 3, 4, 5, 6, 8, 9, 4, 4, 5, 4, 6, 2, 3, 6, 1, 3, 4, 6, 8, 1, 6, 9, 9, 3, 4, 2, 4, 5, 7, 8, 5, 1, 2, 3, 5, 6, 8, 9, 2, 3, 5, 7, 8, 9, 1, 3, 4, 5, 6, 4, 5, 7, 2, 4, 5, 7, 8, 6, 9, 3, 4, 5, 8, 1, 2, 3, 4, 5, 8, 2, 3, 4, 5, 6, 7, 8, 9, 2, 7, 2, 3, 4, 5, 6, 7, 8, 9, 3, 8, 3, 4, 5, 6, 7, 8, 3, 2, 2, 7, 1, 2, 3, 4, 5, 6, 7, 8, 9, 1, 3, 6, 8, 4, 9, 5, 6, 7, 3, 2, 7, 1, 2, 3, 4, 5, 6, 7, 8, 9, 5, 4, 8, 3, 7, 1, 4, 5, 6, 7, 8, 9, 3, 7, 7, 1, 6, 2, 3, 4, 6, 7, 4, 5, 8, 5, 6, 7, 8, 5, 9, 4, 1, 2, 3, 4, 6, 7, 8, 7, 1, 2, 3, 5, 6, 8, 9, 4, 6, 1, 4, 8, 1, 5, 6, 8, 9, 2, 4, 5, 9, 2, 2, 9, 2, 1, 3, 7, 2, 3, 4, 5, 6, 8, 1, 3, 5, 7, 8, 8, 3, 4, 8, 1, 2, 3, 4, 5, 6, 7, 8, 9, 5, 3, 4, 2, 7, 6, 1, 5, 6, 5, 9, 8, 9, 3, 7, 2, 3, 4, 5, 6, 7, 8, 9, 7, 2, 3, 7, 7, 2, 7, 9, 7, 2, 3, 6, 7, 2, 3, 4, 8, 9 ],
"Freq": [ 0.9943902, 0.995893, 0.9964803, 0.6709247, 0.1054631, 0.06282907, 0.1593166, 0.002243895, 0.9959666, 0.1672663, 0.07464033, 0.1016188, 0.5359715, 0.009892091, 0.05395686, 0.05575542, 0.3739602, 0.001352478, 0.01284854, 0.01420102, 0.5044744, 0.08723485, 0.004733674, 0.9873084, 0.9753126, 0.01912378, 0.6929069, 0.134917, 0.08161644, 0.088279, 0.003241695, 0.09508972, 0.4603207, 0.05294768, 0.116701, 0.1610042, 0.1102176, 0.1548593, 0.1145668, 0.1296158, 0.2203954, 0.1310721, 0.1844719, 0.06505062, 0.9904512, 0.9433326, 0.04287875, 0.01324226, 0.003310564, 0.03972677, 0.827641, 0.1158697, 0.9865414, 0.9902387, 0.1937147, 0.8054455, 0.05891628, 0.932841, 0.9954557, 0.9948727, 0.9960342, 0.8489162, 0.05042382, 0.008979585, 0.09186806, 0.2230818, 0.7759832, 0.2071853, 0.02825254, 0.004956586, 0.1630717, 0.2745949, 0.02726122, 0.2944212, 0.9753121, 0.1954346, 0.0222647, 0.007421567, 0.6308332, 0.1286405, 0.01236928, 0.002473856, 0.01925943, 0.2311131, 0.7463029, 0.01217584, 0.9740669, 0.01176028, 0.9761034, 0.01082065, 0.1125347, 0.7541992, 0.03570814, 0.04544672, 0.04111846, 0.1591809, 0.04138704, 0.03183618, 0.006367236, 0.7577011, 0.006367236, 0.07064442, 0.1812183, 0.1081167, 0.3495363, 0.07494451, 0.09521639, 0.1204027, 0.9846743, 0.9712883, 0.01566594, 0.1238557, 0.3318852, 0.5435222, 0.9991276, 0.0005079449, 0.1854727, 0.2635665, 0.1157461, 0.05996486, 0.1269024, 0.08855276, 0.001394532, 0.1589766, 0.08011836, 0.9190047, 0.08565257, 0.8639444, 0.0006744296, 0.04923336, 0.1449868, 0.6999363, 0.1549859, 0.05617111, 0.9212062, 0.01123422, 0.9572035, 0.08769904, 0.9081094, 0.002829001, 0.9888274, 0.009285925, 0.04642963, 0.9378784, 0.2308028, 0.001433558, 0.09461482, 0.04730741, 0.5146473, 0.06307655, 0.01433558, 0.03440539, 0.9924005, 0.9851474, 0.954796, 0.6439042, 0.1076874, 0.05217845, 0.1509844, 0.04551737, 0.9533698, 0.6873581, 0.09091309, 0.1639191, 0.05509884, 0.001377471, 0.9697604, 0.02486565, 0.983295, 0.9832432, 0.983295, 0.1403811, 0.8595572, 0.9907787, 0.9966191, 0.2346584, 0.06601643, 0.3210799, 0.3450859, 0.03300822, 0.9739646, 0.9774169, 0.9970156, 0.6481896, 0.2924492, 0.05892632, 0.9877359, 0.8200585, 0.001802326, 0.003604653, 0.1730233, 0.9976127, 0.00611909, 0.9729354, 0.01835727, 0.9515497, 0.9977547, 0.001600248, 0.9940952, 0.9873113, 0.01285066, 0.09959264, 0.07389131, 0.05782798, 0.7565828, 0.004063595, 0.1158124, 0.7151927, 0.02844516, 0.08939908, 0.04673134, 0.9931822, 0.00599205, 0.01800699, 0.9723775, 0.6830945, 0.1464368, 0.1260521, 0.04409745, 0.009903249, 0.9853733, 0.04522555, 0.9535054, 0.9923319, 0.3722957, 0.1911222, 0.1235749, 0.09844105, 0.09058671, 0.1235749, 0.9725803, 0.9974897, 0.04333572, 0.01926032, 0.05778096, 0.8811596, 0.08075786, 0.913839, 0.9976223, 0.954345, 0.0274526, 0.3727774, 0.00216731, 0.00216731, 0.5837289, 0.01155899, 0.9753121, 0.9853823, 0.003422848, 0.992626, 0.9796429, 0.9979421, 0.2462266, 0.6181494, 0.003443729, 0.1325836, 0.003795773, 0.01897887, 0.9755137, 0.9991865, 0.05665903, 0.2435809, 0.3516037, 0.1535619, 0.1503847, 0.04500951, 0.1465204, 0.8528674, 0.9237071, 0.07561147, 0.908106, 0.09011739, 0.2304005, 0.0004815058, 0.09822719, 0.02142701, 0.1540819, 0.2371416, 0.04285402, 0.2152331, 0.1623974, 0.03302997, 0.05504995, 0.7459268, 0.001580481, 0.3619301, 0.003160961, 0.6321922, 0.003246685, 0.7564775, 0.05519364, 0.1103873, 0.07467375, 0.04888945, 0.1466684, 0.0511117, 0.6644521, 0.08666766, 0.9779326, 0.6684764, 0.330627, 0.1793232, 0.320071,  0.40869, 0.09070416, 0.001013078, 0.08104626, 0.04052313, 0.8773258, 0.09129573, 0.2790162, 0.0959118, 0.06206058, 0.2102879, 0.1046311, 0.08975703, 0.04564786, 0.02102879, 0.07949224, 0.01987306, 0.01093018, 0.7919414, 0.04372073, 0.05465091, 0.03443119, 0.9591547, 0.004918742, 0.9679666, 0.0158683, 0.105688, 0.8748622, 0.01174312, 0.05845979, 0.2477581, 0.02227039, 0.2999544, 0.03688534, 0.3340559, 0.8536789, 0.01097017, 0.1116963, 0.01894848, 0.004986442, 0.9971527, 0.05484341, 0.5634719, 0.003538285, 0.05572799, 0.1963748, 0.1264937, 0.02515161, 0.1620882, 0.03074086,   0.7797, 0.002794624, 0.06236935, 0.4409622, 0.3392017, 0.1542821, 0.002188398, 0.04624015, 0.5005496, 0.09016829, 0.02658808, 0.1653085, 0.06936022, 0.07167223, 0.009248029, 0.02196407, 0.9819285, 0.9668412, 0.9964721, 0.9709572, 0.2673305, 0.1562855, 0.09283126, 0.4826638, 0.0005875396, 0.0002937698, 0.9799806, 0.0131541, 0.03110272, 0.09547812, 0.6343509, 0.2386953, 0.9948851, 0.9926458, 0.9938132, 0.003511708, 0.961609, 0.9684579, 0.02653309, 0.9897261, 0.01964083, 0.04146398, 0.008729259, 0.7332578, 0.1811321, 0.0152762, 0.9865414, 0.06190931, 0.1708697, 0.7280535, 0.02971647, 0.00990549, 0.9980192,  0.98298, 0.006344722, 0.8501928, 0.1332392, 0.006344722, 0.02106208, 0.1194794, 0.3266537, 0.06471803, 0.1340314, 0.02259387, 0.2784024, 0.0245086, 0.009190726, 0.8545206, 0.01081672, 0.1298006, 0.01641022, 0.9682029, 0.9873113, 0.9497605, 0.04522669, 0.9866599, 0.9853699, 0.002728294, 0.1909806, 0.805756, 0.9522095, 0.01449735, 0.9761549, 0.00483245, 0.9825065, 0.9649562, 0.1762062, 0.1426431, 0.001678154, 0.6544802, 0.02349416, 0.9688425, 0.9547668, 0.01440469, 0.04321406, 0.9411061, 0.9678094, 0.03104549, 0.9867354, 0.9892745, 0.008716075, 0.9790904, 0.888609, 0.01586802, 0.04760406, 0.04760406, 0.9883543, 0.001600717, 0.350557, 0.04642079, 0.01280573, 0.5826609, 0.00480215, 0.995834, 0.04168988, 0.008337977, 0.9421914, 0.00337186, 0.9946987, 0.9997744, 0.09749107, 0.2521321, 0.5177112, 0.1311087, 0.02983502, 0.09477006, 0.02427751, 0.001170001, 0.836258, 0.01374751, 0.1561584, 0.05465545, 0.03279327, 0.3443293, 0.05621703, 0.04216278, 0.08354476, 0.1717743, 0.0593402, 0.0006936069, 0.002774428, 0.9960196, 0.03029787, 0.9392341, 0.201526, 0.794908, 0.1166718, 0.5000221, 0.1311169, 0.005555801, 0.04000176, 0.08333701, 0.1233388, 0.7210949, 0.1051763, 0.1737002, 0.04744707, 0.232922, 0.670729, 0.04960375, 0.9864559, 0.01283493, 0.9679718, 0.9921139, 0.069616, 0.2187931, 0.7094201, 0.9222077, 0.05424751, 0.01972637, 0.01671683, 0.9194258, 0.05850891, 0.04152165, 0.00244245, 0.9549979, 0.9988917, 0.9805819, 0.9758507, 0.01424599, 0.007122997, 0.9417007, 0.02942815, 0.9968404, 0.05149336, 0.9449031, 0.6896936, 0.04407816, 0.04407816, 0.1789055, 0.04667099, 0.9882939, 0.03868462, 0.005275176, 0.8844712, 0.001758392, 0.06857729, 0.01527133, 0.9804193, 0.003054266, 0.9943539, 0.9859822, 0.008355781, 0.9982447, 0.6393642, 0.0002600098, 0.0106604, 0.3049915, 0.002860108, 0.04186158, 0.9992243, 0.9954593, 0.02837476, 0.964742, 0.8955584, 0.06223372, 0.003035791, 0.03794739, 0.9932665, 0.0004914572, 0.324116, 0.03882512, 0.2275447, 0.2098522, 0.1968286, 0.001965829, 0.9768013, 0.02108204, 0.08278856, 0.1580509, 0.003763117, 0.7526233, 0.9572035, 0.01844653, 0.01844653, 0.009223267, 0.8439289, 0.0968443, 0.004611634, 0.004611634,  0.98822, 0.6932422, 0.001873628, 0.1330276, 0.003747255, 0.110544, 0.05620883, 0.9820784, 0.9943743, 0.7251309, 0.2456914, 0.02729904, 0.01252283, 0.982148, 0.005366929, 0.9957121, 0.009690023, 0.006460016, 0.03553009, 0.9463923, 0.4171967, 0.5798327, 0.001767783, 0.9875459, 0.9977495, 0.9863622, 0.0439991, 0.955409, 0.134047, 0.0240273, 0.05058379, 0.2579773, 0.01264595, 0.521013, 0.9707335, 0.0250189, 0.9955854, 0.09019214, 0.7131192, 0.08297677, 0.001202562, 0.09740751, 0.01443074, 0.04059715, 0.4158733, 0.295072, 0.03960698, 0.02079366, 0.002970523, 0.1732805, 0.01386244, 0.05173819, 0.1578342, 0.08775844, 0.1191943, 0.3634771, 0.06287172, 0.007204051, 0.1473556, 0.003274569, 0.9981016, 0.1017837, 0.09264144, 0.0006094832, 0.04510175, 0.3821459, 0.0006094832, 0.0146276, 0.3626425, 0.9856587, 0.1840978, 0.1491426, 0.004660705, 0.6618201, 0.9688425, 0.9965957, 0.9845129, 0.01562719, 0.9755664, 0.995351, 0.1371458, 0.861195, 0.1227923, 0.08716342, 0.199776, 0.02417671, 0.08143735, 0.360742, 0.006362293, 0.07253014, 0.04517228, 0.03003332, 0.931033, 0.03754165, 0.9899257, 0.9792305, 0.01794918, 0.007692505, 0.002564168, 0.005128336, 0.08461755, 0.8820739, 0.287856, 0.192362, 0.01167912, 0.5076983, 0.7944754, 0.05654629, 0.144193, 0.004240972, 0.9920263, 0.004862874, 0.9988449, 0.9984607, 0.8838835, 0.03260929, 0.0240279, 0.0008581393, 0.001716279, 0.05663719, 0.9921733, 0.9847058, 0.9861386, 0.009391796, 0.01124841, 0.978612, 0.9843472, 0.3511167, 0.08598777, 0.5499634, 0.01253988, 0.1221592, 0.07150784, 0.07448733, 0.694222, 0.03575392, 0.9826134, 0.01747731, 0.9914442, 0.9862138, 0.02678897, 0.9644028, 0.9936585, 0.9847434, 0.9979643, 0.9936824, 0.9706607, 0.1054172, 0.1071084, 0.4340709, 0.06426504, 0.09696128, 0.1916677, 0.9994213, 0.004330923, 0.3194056, 0.1223486, 0.04114377, 0.1559132, 0.3161574, 0.04006104, 0.2574589, 0.1054611, 0.09139959, 0.07633372, 0.05323273, 0.2216356, 0.04118003, 0.1175138, 0.03582328, 0.9577991, 0.03717773, 0.003780786, 0.000630131, 0.1358235, 0.1174944, 0.1424032, 0.396661, 0.006579685, 0.0897657, 0.1113847, 0.9921191, 0.1080733, 0.04011454, 0.1283665, 0.09910652, 0.0009438716, 0.558772, 0.007079037, 0.05710423, 0.9804811, 0.1010546, 0.3010437, 0.3130572, 0.1618287, 0.07208089, 0.05088063, 0.9862247, 0.04961109, 0.02204937, 0.07166046, 0.8544132, 0.9790811, 0.002529925, 0.01770948, 0.9957679, 0.7805929, 0.04308793, 0.004008179, 0.04408997, 0.1282617, 0.9862894, 0.03204278, 0.2683583, 0.5140196, 0.1461952, 0.002670232, 0.03738324, 0.9789628, 0.6002749, 0.09720149, 0.002225988, 0.1788211, 0.02671186, 0.04377777, 0.04971374, 0.07586855, 0.9220947, 0.9706607, 0.9960498, 0.961609, 0.9935062, 0.9522095, 0.09806929, 0.9004544, 0.9762467, 0.9921145, 0.9809032, 0.9791215, 0.9925729, 0.9843472, 0.8761825, 0.1164159, 0.00612715, 0.01298432, 0.9738237, 0.9692942, 0.9967115, 0.03201177, 0.9079702, 0.05820322, 0.0009700536, 0.04056374, 0.9587793, 0.01654882, 0.8837073, 0.09598318, 0.9907273, 0.9515497, 0.00228696, 0.9376536, 0.057174, 0.9855494, 0.01409477, 0.03672401, 0.9609451, 0.05251474, 0.9452653, 0.9993164, 0.9521004, 0.04667159, 0.172551, 0.03210251, 0.008025628, 0.7865115, 0.9645038, 0.02857789, 0.0354249, 0.5533032, 0.2783385, 0.1315782, 0.9941473, 0.5172729, 0.2310076, 0.04988537, 0.1673078, 0.02455895, 0.009209606, 0.01203105, 0.9263907, 0.06015524, 0.00140147, 0.00140147, 0.2943088, 0.2060161, 0.470894, 0.02522646, 0.903174, 0.002163291, 0.008653164, 0.001081645, 0.001081645, 0.04326582, 0.04002088, 0.975441, 0.9615508, 0.9931404, 0.008486724, 0.5529427, 0.06658814, 0.1233839, 0.1090218, 0.05614294, 0.06789379, 0.01632062, 0.01984138, 0.1663247, 0.2897822, 0.2452003, 0.04139745, 0.2371168, 0.9791259, 0.1087042, 0.1234983,   0.0759, 0.5994813, 0.01608051,   0.0759, 0.03420312, 0.0006577524, 0.3032239, 0.3611061, 0.2525769, 0.04801593, 0.00866453, 0.1357443, 0.005776353, 0.7971367, 0.002888177, 0.049099, 0.2171035, 0.0005566756, 0.2454939, 0.0478741, 0.02616375, 0.0979749, 0.1736828, 0.1914964, 0.9979291, 0.004823071, 0.06350377, 0.008038452, 0.07395376, 0.1061076, 0.09646142, 0.04260379, 0.003215381, 0.6012762, 0.2614431, 0.03555188, 0.02078418, 0.6820492, 0.9978657, 0.9891352, 0.990896, 0.9582398, 0.03342697, 0.9500728, 0.9930771, 0.9925123, 0.9956088, 0.009937219, 0.9837847, 0.9956088, 0.946488, 0.9936362, 0.9780417, 0.01546598, 0.5877072, 0.215419, 0.0519215, 0.09721473, 0.03203667, 0.9735577, 0.9658048, 0.02299535, 0.8864537, 0.007934085, 0.07501317, 0.03101506, 0.9694257, 0.9956088, 0.9830244, 0.01260288, 0.1639686, 0.006072912, 0.825916, 0.984671, 0.9967019, 0.9706607, 0.9931048, 0.991318, 0.9844842, 0.9581522, 0.000900519, 0.000900519, 0.02881661, 0.005403114, 0.005403114, 0.1266272, 0.06954656, 0.003936598, 0.09579054, 0.2132324, 0.04002208, 0.2348837, 0.07610756, 0.1397492, 0.1170439, 0.00836028, 0.00836028, 0.01672056, 0.7482451, 0.09614322, 0.07160009, 0.9250731, 0.1434313, 0.2104144, 0.4295658, 0.2162391, 0.09720078, 0.004165748, 0.001388583, 0.1777386, 0.2513335, 0.09997795, 0.369363, 0.8979966, 0.100522, 0.9747768, 0.9951628, 0.1304283, 0.0156514, 0.8295241, 0.02399881, 0.9956088, 0.3325277, 0.06387357, 0.0003209727, 0.2250019, 0.1563137, 0.02985046, 0.1829544, 0.008987236, 0.9968446, 0.3712256, 0.1653358, 0.05303222, 0.004679314, 0.4055405, 0.002698813, 0.0008996044, 0.07286795, 0.7142859, 0.03598417, 0.06477151, 0.09445846, 0.01439367, 0.9843472, 0.9336099, 0.04787743, 0.9965671, 0.002378442, 0.0007261219, 0.8706202, 0.1285236, 0.9973323, 0.02589903, 0.3688022, 0.3874495, 0.213408, 0.004143844, 0.006532998, 0.9080867, 0.013066, 0.06859648, 0.6015361, 0.2022709, 0.1952354, 0.9940325, 0.8523167, 0.007776612, 0.139979, 0.725005, 0.05459757, 0.0457096, 0.0006348555, 0.1739504, 0.1554735, 0.0588278, 0.04254511, 0.07248426, 0.3429871, 0.02626241, 0.03519163, 0.2668261, 0.1321862, 0.01201693, 0.8051343, 0.01201693, 0.03605079, 0.9960365, 0.03874022, 0.9491353, 0.9852927, 0.9856433, 0.3674356, 0.1796108, 0.04435512, 0.1368985, 0.1549691, 0.05914016, 0.05859256, 0.8726767, 0.1266059, 0.101479, 0.2215496, 0.1084509, 0.4779584, 0.06119727, 0.003098596, 0.02633806, 0.009478318, 0.985745, 0.9863378, 0.09321417, 0.7700301, 0.1337421, 0.9632577, 0.9945443, 0.9447352, 0.05079221, 0.9964803, 0.002061401, 0.03298241, 0.1010086, 0.7029377, 0.1298683, 0.03298241, 0.1228972, 0.01843458, 0.8541356, 0.2775986, 0.1100611, 0.5686492, 0.002445803, 0.002445803, 0.03790995, 0.1108893, 0.0162277, 0.5246955, 0.3461909, 0.001352308, 0.01389837, 0.9450889, 0.02779673, 0.04428219, 0.7153276, 0.1600971, 0.04768851, 0.001703161, 0.0306569, 0.005566908, 0.008350363, 0.9853428, 0.345599, 0.1646814, 0.04020391, 0.3084877, 0.09741716, 0.04252337, 0.1372596, 0.6467988, 0.09084807, 0.1244224, 0.0001417977, 0.1745529, 0.6366716, 0.1334316, 0.0550175, 0.8379169,  0.14837, 0.01387633, 0.02255805, 0.2575984, 0.1040581, 0.2779734, 0.2750627, 0.0625804, 0.1057743, 0.2502696, 0.2361034, 0.01038855, 0.3975981, 0.8062982, 0.03406894, 0.1362758, 0.02271263, 0.06327279, 0.1998088, 0.006660294, 0.7326323, 0.03863146, 0.5987876, 0.1385694, 0.08146198, 0.1410888, 0.9959532, 0.06142014, 0.3269891, 0.05791041, 0.03334236, 0.08540324, 0.2386611, 0.1228403, 0.04504143, 0.02807778, 0.8448477, 0.02988848, 0.01394796, 0.001992565, 0.045829, 0.05379926, 0.009962827, 0.9865414, 0.975441, 0.05917959, 0.1003939, 0.5474112, 0.2916708, 0.001056778, 0.7565352, 0.1572666, 0.07201155, 0.01489894, 0.9594499, 0.6262175, 0.1060694, 0.05099491, 0.01937807, 0.008159186, 0.1121888, 0.07649237, 0.9931587, 0.01808695, 0.009043473, 0.009043473, 0.9586082, 0.1563882, 0.00601493, 0.8300604, 0.7642651, 0.2352312, 0.04569262, 0.06821716, 0.003861349, 0.2458392, 0.6364789, 0.0660429, 0.003071763, 0.1628034, 0.7679407, 0.999165, 0.07425364, 0.2609485, 0.002121533, 0.002121533, 0.6110014, 0.04667372, 0.06125513, 0.4888159, 0.09923331, 0.1837654, 0.05390452, 0.1127094, 0.007707943, 0.04881697, 0.0179852, 0.8709976, 0.04881697, 0.005138629, 0.009702225, 0.009702225, 0.0776178, 0.8732002, 0.02910667, 0.9547668, 0.3736074, 0.144583, 0.3079983, 0.03401954, 0.03644951, 0.1026661, 0.0307594, 0.9681117, 0.02537795, 0.0482181, 0.9212195, 0.002537795, 0.1663522, 0.06031379, 0.1375297, 0.04216628, 0.4503074, 0.07810547, 0.06493963, 0.1401151, 0.09218099, 0.01106172, 0.01474896, 0.0184362, 0.1991109, 0.04793411, 0.4756539, 0.09359058, 0.1871812, 0.1570418, 0.006345124, 0.4838157, 0.01744909, 0.05393356, 0.9285398, 0.006929402, 0.003464701, 0.05889992, 0.005251835, 0.5803277, 0.1417995, 0.1286699, 0.1116015, 0.03282397, 0.1103598, 0.5384589, 0.01010621, 0.2946971, 0.0250634, 0.02102092, 0.09388382, 0.8360131, 0.06705987, 0.238669, 0.01079693, 0.03807338, 0.07160069, 0.3062918, 0.1647952, 0.09035325, 0.0784198, 0.001136519, 0.1043935, 0.0187821, 0.1065775, 0.1017728, 0.3878723, 0.0008735862, 0.1633606, 0.076002, 0.04018496, 0.9728276, 0.9919222, 0.1005535, 0.1708198, 0.02180679, 0.0920731, 0.4676344, 0.08843864, 0.05936292, 0.001211488, 0.08066742, 0.03931689, 0.7992175, 0.07998954, 0.9895511, 0.08905126, 0.1521148, 0.758495, 0.000346503, 0.9902527, 0.9656963, 0.9942972, 0.9913076, 0.9745876, 0.001733603, 0.3718578, 0.001733603, 0.6232303, 0.0008668015, 0.2267566, 0.005889781, 0.1384098, 0.6272617, 0.2238232, 0.09780815, 0.5901458, 0.0007326453, 0.03480065, 0.05275046, 0.9946294, 0.060518, 0.9228994, 0.9792254, 0.007095836, 0.007095836, 0.7421201, 0.007703669, 0.2157027, 0.03338256, 0.09595717, 0.1854453, 0.00107817, 0.7159052, 0.2596814, 0.1577324, 0.5809168, 0.993928, 0.9759317, 0.1852885, 0.8115636, 0.0520801, 0.07785169, 0.07999932, 0.0005369082, 0.4048288, 0.04402647, 0.1991929, 0.06711353, 0.07463024, 0.980068, 0.3467446, 0.02938513, 0.009795044, 0.03056054, 0.07091612, 0.03408675, 0.4783899, 0.2110103, 0.7876754, 0.9890936, 0.003090918, 0.006181835, 0.1675828, 0.832611, 0.970891, 0.01855206, 0.006184019, 0.02260961, 0.114663, 0.02583955, 0.3811334, 0.1687646, 0.1041657, 0.1824919, 0.2427505, 0.7543937, 0.9632577, 0.1064175, 0.6669589, 0.2219402, 0.00455262, 0.004595822, 0.9926977, 0.9940373, 0.9668412, 0.0147227, 0.04983066, 0.2231055, 0.4428134, 0.03171042, 0.001132515, 0.2163104, 0.02151779, 0.9950075, 0.9955076, 0.993027, 0.9969759, 0.9865414, 0.06724915, 0.9243462, 0.007911665, 0.0007346998, 0.4628609, 0.2652266, 0.2534714, 0.0176328, 0.5285619, 0.4705969, 0.0004912285, 0.9653695, 0.9577956, 0.03780772, 0.02120648, 0.03550852, 0.6014255, 0.07422267, 0.2677934, 0.9689658, 0.02215126, 0.2288963, 0.4179204, 0.07236077, 0.1188784, 0.04577926, 0.09377365, 0.1306442, 0.0580641, 0.7572526, 0.0387094, 0.007258012, 0.007258012, 0.03344333, 0.03344333, 0.07524748, 0.008360831, 0.844444, 0.9943526, 0.004231288, 0.9789628, 0.1375771, 0.0144818, 0.690299, 0.08447715, 0.07240899, 0.06016587, 0.9382115, 0.727435, 0.1513422, 0.07046096, 0.0506128, 0.002276411, 0.001365846, 0.7507603, 0.1720967, 0.03778842, 0.03551201, 0.6584874, 0.07344033, 0.05322361, 0.02475517, 0.03218172, 0.155545, 0.0004125861, 0.001650344, 0.9845048, 0.01036321, 0.05660371, 0.4746004, 0.1932146, 0.06803331, 0.06458629, 0.0009071108, 0.08726406, 0.05497091, 0.9758762, 0.0114809, 0.05639103, 0.120712, 0.007929988, 0.2713818, 0.1233554, 0.4202894, 0.9964803, 0.9953325, 0.1306135, 0.8672736, 0.00778924, 0.1421536, 0.119435, 0.1239787, 0.002596413, 0.06880495, 0.0395953, 0.4115315, 0.08373433, 0.9611828, 0.001209796, 0.03629388, 0.0006048979, 0.9958602, 0.9875616, 0.05239822, 0.01309955, 0.9300684, 0.9759479, 0.9850086, 0.01026051, 0.08102422, 0.2531042, 0.01543318, 0.03935462, 0.246931, 0.09259911, 0.1960014, 0.02623641, 0.04938619, 0.9709572, 0.2098543, 0.7895508, 0.8459051, 0.1530365, 0.438802, 0.08108297, 0.02991832, 0.001300796, 0.1855803, 0.2029242, 0.06070383, 0.08978759, 0.9097487, 0.9956466, 0.881249, 0.1170222, 0.01335533, 0.7326354, 0.2155932, 0.03625019, 0.001907905, 0.0986893, 0.0317813, 0.8681313, 0.8052517, 0.1666038, 0.02313942, 0.9952464, 0.990638, 0.9842363, 0.9909466, 0.2438387, 0.0417235, 0.023842, 0.2850203, 0.09320055, 0.02167455, 0.2904389, 0.9926847, 0.4987318, 0.1637459, 0.1907246, 0.06369978, 0.02810285, 0.03334871, 0.02173287, 0.9958075, 0.001915014, 0.1047248, 0.005511829, 0.8874045, 0.9783454, 0.01811751, 0.9823795, 0.007538203, 0.9875045, 0.008621011, 0.008621011, 0.06034708, 0.9224482, 0.9914442, 0.9913618, 0.9931976, 0.9882939, 0.02278306, 0.7898127, 0.1822645, 0.7524568, 0.0102236, 0.1615328, 0.02862607, 0.002044719, 0.04498383, 0.002333061, 0.002333061, 0.2286399, 0.1189861, 0.6462578, 0.9993598, 0.1791239, 0.2935224, 0.5268351, 0.01936305, 0.4610827, 0.04356687, 0.1428025, 0.1355414, 0.06292992, 0.101656, 0.03025477, 0.002420382, 0.9689658, 0.330584, 0.6679147, 0.874083, 0.1235117, 0.9936759, 0.01282921, 0.9750201, 0.009621909, 0.9392603, 0.05870377, 0.9684805, 0.02665543, 0.1430674, 0.8563891, 0.2457464, 0.2395899, 0.03719544, 0.04078672, 0.06900395, 0.3332198, 0.02590855, 0.008208648, 0.9759317, 0.1584201, 0.6635279, 0.1767877, 0.9936311, 0.2426216, 0.7553314, 0.9522095, 0.9773934, 0.7092274, 0.005766077, 0.02018127, 0.2623565, 0.9922984, 0.1136065, 0.007834931, 0.8226677, 0.05484452 ] 
},
"R":       30,
"lambda.step":     0.01,
"plot.opts": {
 "xlab": "PC1",
"ylab": "PC2" 
},
"topic.order": [ 4, 6, 7, 3, 8, 5, 2, 1, 9 ] 
}